{"ونأكل":["h_muslim_3398","h_muslim_4908","h_ahmad_134","h_ahmad_3270","h_darimi_1680"],"ونأكل منها":["h_muslim_3398"],"ونأكل حتى":["h_muslim_4908"],"ونأمر":["h_abu-dawud_776"],"ونأمر بحاجتنا":["h_abu-dawud_776"],"ونأكله":["h_abu-dawud_3241"],"ونأكله فقال":["h_abu-dawud_3241"],"ونأى":["h_abu-dawud_4125"],"ونأى عن":["h_abu-dawud_4125"],"ونأكل الميتة":["h_ahmad_134","h_ahmad_3270"],"ونأتي":["h_ahmad_134","h_ahmad_3270"],"ونأتي الفواحش":["h_ahmad_134","h_ahmad_3270"],"ونأخذ":["h_darimi_41"],"ونأخذ اللحم":["h_darimi_41"],"ونأكل ونحن":["h_darimi_1680"],"ونؤدي":["h_nasai_2374","h_ahmad_1568"],"ونؤدي زكاة":["h_nasai_2374"],"ونؤمن":["h_tirmidzi_2413"],"ونؤمن بها":["h_tirmidzi_2413"],"ونؤدي إليك":["h_ahmad_1568"],"ونادى":["q_11_42","q_11_45","h_muslim_2693","h_muslim_4339","q_43_51","h_abu-dawud_1130","h_abu-dawud_3043","h_abu-dawud_3110","q_7_44","q_7_48","q_7_50","h_bukhari_451","h_ibnu-majah_1597"],"ونادى نوح":["q_11_42","q_11_45"],"ونام":["h_malik_21","h_muslim_1059","h_nasai_616","h_abu-dawud_225","h_bukhari_2672","h_ibnu-majah_657"],"ونام رسول":["h_malik_21","h_muslim_1059","h_ibnu-majah_657"],"ونافع":["h_malik_62","h_muslim_1915","h_muslim_2738","h_muslim_3595","h_muslim_3678","h_nasai_1645","h_nasai_1714","h_tirmidzi_237","h_tirmidzi_506","h_tirmidzi_507","h_tirmidzi_1150","h_tirmidzi_2170","h_tirmidzi_3519","h_abu-dawud_1804","h_abu-dawud_2899","h_abu-dawud_3048","h_abu-dawud_4125","h_bukhari_502","h_bukhari_4792","h_darimi_2225","h_darimi_2281","h_ibnu-majah_3684","h_ibnu-majah_3685"],"ونافع يومئذ":["h_malik_62"],"ونافعا":["h_malik_192","h_abu-dawud_4155"],"ونافعا مولى":["h_malik_192"],"ونار":["h_malik_861","h_muslim_4793","h_muslim_4829","h_tirmidzi_2109","h_abu-dawud_3592","h_ahmad_656","h_ahmad_899","h_ahmad_900","h_ahmad_3549","h_ahmad_3550","h_ibnu-majah_2805","h_ibnu-majah_4007","h_ibnu-majah_4023"],"ونار وشنار":["h_malik_861"],"ونادينه":["q_19_52","q_37_104"],"ونادينه من":["q_19_52"],"ونا":["q_41_51","q_17_83"],"ونا بجانبهۚ":["q_41_51","q_17_83"],"وناضح":["h_muslim_757"],"وناضح قال":["h_muslim_757"],"وناموا":["h_muslim_981","h_nasai_534","h_bukhari_538","h_bukhari_5115","h_ibnu-majah_652","h_ibnu-majah_653"],"وناموا وإنكم":["h_muslim_981","h_bukhari_5115","h_ibnu-majah_652"],"وناحية":["h_muslim_983","h_nasai_527","h_bukhari_537"],"وناحية اللحية":["h_muslim_983","h_bukhari_537"],"ونادوا":["h_muslim_1358","q_43_77","h_tirmidzi_466","h_ahmad_1875","q_7_46","h_bukhari_2997","h_bukhari_4140"],"ونادوا يا":["h_muslim_1358","h_tirmidzi_466","h_ahmad_1875","h_bukhari_2997","h_bukhari_4140"],"وناصيتها":["h_muslim_1473","h_ahmad_4114"],"ونافع مولى":["h_muslim_1915","h_bukhari_502"],"ونائلة":["h_muslim_2091","h_muslim_4181","h_darimi_3"],"ونائلة ثم":["h_muslim_2091"],"ونادى كعب":["h_muslim_2693","h_abu-dawud_3043","h_bukhari_451"],"ونافع معه":["h_muslim_2738"],"وناقة":["h_muslim_2868"],"وناقة منوقة":["h_muslim_2868"],"ونافع عن":["h_muslim_3595","h_nasai_1645","h_nasai_1714","h_tirmidzi_506","h_tirmidzi_507","h_tirmidzi_1150","h_abu-dawud_1804","h_bukhari_4792","h_darimi_2281"],"ونائلة قال":["h_muslim_4181","h_darimi_3"],"ونادى الأنصاري":["h_muslim_4339"],"ونافخ":["h_muslim_4420","h_bukhari_4803"],"ونافخ الكير":["h_muslim_4420","h_bukhari_4803"],"ونار تخرج":["h_muslim_4793","h_tirmidzi_2109","h_ahmad_899","h_ahmad_900","h_ibnu-majah_4007"],"ونار فناره":["h_muslim_4829","h_ahmad_3550","h_ibnu-majah_4023"],"ونارا":["h_muslim_4831","h_muslim_4832","h_bukhari_3136","h_bukhari_6263","h_ibnu-majah_4029"],"ونارا فناره":["h_muslim_4831","h_bukhari_6263","h_ibnu-majah_4029"],"ونارا فأما":["h_muslim_4832","h_bukhari_3136"],"وناسا":["h_nasai_320","h_ahmad_2439"],"وناسا يطلبون":["h_nasai_320"],"وناحية الجبين":["h_nasai_527"],"وناموا وأنتم":["h_nasai_534","h_ibnu-majah_653"],"ونام الناس":["h_nasai_616"],"وناح":["h_nasai_1786"],"وناح أهله":["h_nasai_1786"],"ونادى فرعون":["q_43_51"],"ونادوا يملك":["q_43_77"],"ونافع وسالم":["h_tirmidzi_237"],"وناصح":["h_tirmidzi_1874"],"وناصح هو":["h_tirmidzi_1874"],"وناصح شيخ":["h_tirmidzi_1874"],"ونافع بن":["h_tirmidzi_2170","h_abu-dawud_3048"],"ونافع ثقة":["h_tirmidzi_3519"],"وناشئة":["h_abu-dawud_1094"],"وناشئة الليل":["h_abu-dawud_1094"],"ونادى المنادي":["h_abu-dawud_1130"],"وناقصته":["h_abu-dawud_1152"],"وناقصته فقال":["h_abu-dawud_1152"],"ونافع في":["h_abu-dawud_2899"],"ونادى منادي":["h_abu-dawud_3110"],"وناس":["h_abu-dawud_3485","h_bukhari_2717"],"وناس معه":["h_abu-dawud_3485"],"ونار فمن":["h_abu-dawud_3592"],"ونافع سليمان":["h_abu-dawud_4125"],"ونافعا ورباحا":["h_abu-dawud_4155"],"ونار يجزون":["h_ahmad_656"],"ونال":["h_ahmad_1579"],"ونال رجل":["h_ahmad_1579"],"وناشداها":["h_ahmad_2238"],"وناشداها الله":["h_ahmad_2238"],"ونارك":["h_ahmad_2304","h_ahmad_4138","h_ibnu-majah_3617"],"وناسا قال":["h_ahmad_2439"],"ونار ونهر":["h_ahmad_3549"],"وناره":["h_ahmad_3549"],"وناره جنة":["h_ahmad_3549"],"ونادينه ان":["q_37_104"],"ونادىهما":["q_7_22"],"ونادىهما ربهما":["q_7_22"],"ونادى اصحب":["q_7_44","q_7_48","q_7_50"],"ونادوا اصحب":["q_7_46"],"وناما":["h_bukhari_119"],"وناما فانسل":["h_bukhari_119"],"وناموا أما":["h_bukhari_538"],"ونام النبي":["h_bukhari_2672"],"وناس من":["h_bukhari_2717"],"وناج":["h_bukhari_6533"],"وناج مخدوش":["h_bukhari_6533"],"وناصحوا":["h_darimi_414"],"وناصحوا الله":["h_darimi_414"],"ونافع ورباح":["h_darimi_2225","h_ibnu-majah_3685"],"ونادى مناد":["h_ibnu-majah_1597"],"ونافع ويسار":["h_ibnu-majah_3684"],"ونبت":["h_malik_927","h_malik_928"],"ونبت شعره":["h_malik_927","h_malik_928"],"ونبيك":["h_malik_1368","h_tirmidzi_3145","h_tirmidzi_3205","h_tirmidzi_3284","h_abu-dawud_4236","h_bukhari_239","h_darimi_2212","h_ibnu-majah_3069","h_ibnu-majah_3800","h_ibnu-majah_3830"],"ونبيك وإني":["h_malik_1368","h_tirmidzi_3205","h_ibnu-majah_3069"],"ونبيك وإنه":["h_malik_1368","h_tirmidzi_3205"],"ونبيا":["q_3_39"],"ونبيا من":["q_3_39"],"ونبي":["h_muslim_552","h_muslim_4013","h_nasai_443","h_abu-dawud_572","h_abu-dawud_2440","h_ahmad_828","h_ahmad_1779","h_bukhari_2968"],"ونبي الله":["h_muslim_552","h_abu-dawud_572","h_abu-dawud_2440","h_ahmad_828"],"ونبيها":["h_muslim_3922"],"ونبيها حي":["h_muslim_3922"],"ونبي التوبة":["h_muslim_4013"],"ونبي الرحمة":["h_muslim_4013"],"ونبي ثم":["h_nasai_443","h_ahmad_1779"],"ونبي فلما":["h_nasai_443","h_ahmad_1779","h_bukhari_2968"],"ونبهه":["h_nasai_3045","h_abu-dawud_2089","h_darimi_1955"],"ونبهه أجرا":["h_nasai_3045"],"ونبله":["h_nasai_3422","h_abu-dawud_2087"],"ونبله ومن":["h_nasai_3422","h_abu-dawud_2087"],"ونبتاعها":["h_nasai_3630","h_nasai_4171"],"ونبتاعها وكنا":["h_nasai_3630"],"ونبذهم":["h_nasai_3762"],"ونبذهم في":["h_nasai_3762"],"ونبهته":["h_nasai_3912"],"ونبهته أجر":["h_nasai_3912"],"ونبتاعها ونسمي":["h_nasai_4171"],"ونبلوكم":["q_21_35"],"ونبلوكم بالشر":["q_21_35"],"ونبئهم":["q_54_28","q_15_51"],"ونبئهم ان":["q_54_28"],"ونبيشة":["h_tirmidzi_704","h_tirmidzi_1430"],"ونبيشة وبشر":["h_tirmidzi_704"],"ونبيشة وأبي":["h_tirmidzi_1430"],"ونبيح":["h_tirmidzi_1639"],"ونبيح ثقة":["h_tirmidzi_1639"],"ونبذ":["h_tirmidzi_1663"],"ونبذ الناس":["h_tirmidzi_1663"],"ونبيك الذي":["h_tirmidzi_3145","h_tirmidzi_3284","h_abu-dawud_4236","h_bukhari_239","h_darimi_2212","h_ibnu-majah_3830"],"ونباتاۙ":["q_78_15"],"ونبش":["h_abu-dawud_371"],"ونبش قبور":["h_abu-dawud_371"],"ونبسط":["h_abu-dawud_1346","h_ibnu-majah_2154"],"ونبسط بعضه":["h_abu-dawud_1346","h_ibnu-majah_2154"],"ونبهه أجر":["h_abu-dawud_2089","h_darimi_1955"],"ونبذها":["h_abu-dawud_2254"],"ونبقى":["h_abu-dawud_2295","h_darimi_347"],"ونبقى فأبى":["h_abu-dawud_2295"],"ونبلوا۟":["q_47_31"],"ونبلوا۟ اخباركم":["q_47_31"],"ونبلي":["h_ahmad_1137"],"ونبلي فجعلت":["h_ahmad_1137"],"ونبي قال":["h_ahmad_1779"],"ونبئهم عن":["q_15_51"],"ونبي فأتينا":["h_bukhari_2968"],"ونبي فرفع":["h_bukhari_2968"],"ونبلغه":["h_bukhari_3175"],"ونبلغه من":["h_bukhari_3175"],"ونبقى فقال":["h_darimi_347"],"ونبعث":["h_ibnu-majah_1513"],"ونبعث إليهما":["h_ibnu-majah_1513"],"ونبيع":["h_ibnu-majah_2778"],"ونبيع وهو":["h_ibnu-majah_2778"],"ونبيك وإنك":["h_ibnu-majah_3069"],"ونبيك وأعوذ":["h_ibnu-majah_3800"],"ونبيك اللهم":["h_ibnu-majah_3800"],"ونبيي":["h_ibnu-majah_4219"],"ونبيي محمد":["h_ibnu-majah_4219"],"ونتف":["h_malik_1429","h_muslim_370","h_muslim_371","h_muslim_372","h_muslim_377","h_nasai_9","h_nasai_10","h_nasai_11","h_nasai_14","h_nasai_4708","h_nasai_4710","h_nasai_4711","h_nasai_4712","h_nasai_4869","h_tirmidzi_2613","h_tirmidzi_2614","h_tirmidzi_2616","h_abu-dawud_49","h_abu-dawud_3552","h_abu-dawud_3554","h_ahmad_1668","h_bukhari_5134","h_bukhari_5136","h_bukhari_5518","h_ibnu-majah_256","h_ibnu-majah_257","h_ibnu-majah_258","h_ibnu-majah_259"],"ونتف الإبط":["h_malik_1429","h_muslim_370","h_muslim_371","h_muslim_372","h_muslim_377","h_nasai_9","h_nasai_10","h_nasai_11","h_nasai_14","h_nasai_4708","h_nasai_4710","h_nasai_4712","h_nasai_4869","h_tirmidzi_2613","h_tirmidzi_2614","h_tirmidzi_2616","h_abu-dawud_49","h_abu-dawud_3552","h_abu-dawud_3554","h_bukhari_5134","h_bukhari_5518","h_ibnu-majah_256","h_ibnu-majah_257","h_ibnu-majah_258","h_ibnu-majah_259"],"ونتحدث":["h_muslim_3715"],"ونتحدث قال":["h_muslim_3715"],"ونتنهم":["h_muslim_4834","h_tirmidzi_2166","h_ahmad_1657","h_ibnu-majah_4027"],"ونتنهم فيرغب":["h_muslim_4834","h_ahmad_1657"],"ونتف الضبع":["h_nasai_4711"],"ونتخذ":["h_nasai_5044"],"ونتخذ دورا":["h_nasai_5044"],"ونتنهم ودماؤهم":["h_tirmidzi_2166","h_ibnu-majah_4027"],"ونتجاوز":["q_46_16"],"ونتجاوز عن":["q_46_16"],"ونتغدى":["h_abu-dawud_905","h_bukhari_5502"],"ونتغدى بعد":["h_abu-dawud_905","h_bukhari_5502"],"ونتركه":["h_abu-dawud_3423"],"ونتركه على":["h_abu-dawud_3423"],"ونتبع":["q_14_44"],"ونتبع الرسلۗ":["q_14_44"],"ونتف أذنابها":["h_ahmad_1668"],"ونتحرج":["h_bukhari_654"],"ونتحرج فقال":["h_bukhari_654"],"ونتجت":["h_bukhari_4068"],"ونتجت خيله":["h_bukhari_4068"],"ونتعجب":["h_bukhari_5083"],"ونتعجب منه":["h_bukhari_5083"],"ونتف الآباط":["h_bukhari_5136"],"ونتحمله":["h_darimi_99"],"ونتحمله نحن":["h_darimi_99"],"ونتخوفه":["h_ibnu-majah_5"],"ونتخوفه فقال":["h_ibnu-majah_5"],"ونثر":["h_nasai_90","h_abu-dawud_98","h_darimi_463"],"ونثر بيده":["h_nasai_90","h_darimi_463"],"ونثر من":["h_abu-dawud_98"],"ونثرا":["h_abu-dawud_1159"],"ونثرا كنثر":["h_abu-dawud_1159"],"ونثرت":["h_ibnu-majah_2018"],"ونثرت له":["h_ibnu-majah_2018"],"ونجينهم":["q_11_58"],"ونجينهم من":["q_11_58"],"ونجنا":["q_10_86","h_abu-dawud_812","h_ibnu-majah_3790"],"ونجنا برحمتك":["q_10_86"],"ونجينا":["q_41_18"],"ونجينا الذين":["q_41_18"],"ونجدة":["h_muslim_3155","h_tirmidzi_1479"],"ونجدة ففرح":["h_muslim_3155"],"ونجعل":["h_nasai_1832","q_34_33","h_ahmad_2882","h_bukhari_1824","h_bukhari_3451","h_bukhari_5662","q_28_35"],"ونجعل على":["h_nasai_1832","h_ahmad_2882","h_bukhari_3451","h_bukhari_5662"],"ونجه":["h_nasai_1913"],"ونجه من":["h_nasai_1913"],"ونجينه":["q_21_71","q_21_74","q_21_88","q_37_76"],"ونجينه ولوطا":["q_21_71"],"ونجينه من":["q_21_74","q_21_88"],"ونجوىهم":["q_43_80","q_9_78"],"ونجوىهم ۗ":["q_43_80"],"ونجدة فقال":["h_tirmidzi_1479"],"ونجني":["q_66_11","q_26_118"],"ونجني من":["q_66_11"],"ونجعل له":["q_34_33"],"ونجوىهم وان":["q_9_78"],"ونجنا من":["h_abu-dawud_812","h_ibnu-majah_3790"],"ونجني ومن":["q_26_118"],"ونجينه واهله":["q_37_76"],"ونجينهما":["q_37_115"],"ونجينهما وقومهما":["q_37_115"],"ونجاهد":["h_bukhari_1728"],"ونجاهد معكم":["h_bukhari_1728"],"ونجعل لهم":["h_bukhari_1824"],"ونجوا":["h_bukhari_2313","h_bukhari_2489"],"ونجوا جميعا":["h_bukhari_2313"],"ونجوا أنفسهم":["h_bukhari_2489"],"ونجاة":["h_darimi_2250"],"ونجاة من":["h_darimi_2250"],"ونجعلهم":["q_28_5"],"ونجعلهم اىمة":["q_28_5"],"ونجعلهم الورثين":["q_28_5"],"ونجعل لكما":["q_28_35"],"ونجيح":["h_ibnu-majah_3684"],"ونجيح وأفلح":["h_ibnu-majah_3684"],"ونحن":["q_29_46","h_malik_166","h_malik_304","h_malik_629","h_malik_820","h_malik_823","h_malik_1274","q_3_84","q_3_181","q_2_30","q_2_133","q_2_136","q_2_138","q_2_139","q_2_247","h_muslim_13","h_muslim_212","h_muslim_536","h_muslim_593","h_muslim_601","h_muslim_624","h_muslim_958","h_muslim_1047","h_muslim_1061","h_muslim_1255","h_muslim_1331","h_muslim_1332","h_muslim_1412","h_muslim_1451","h_muslim_1471","h_muslim_1473","h_muslim_1511","h_muslim_1518","h_muslim_1519","h_muslim_1568","h_muslim_1670","h_muslim_1728","h_muslim_1790","h_muslim_1797","h_muslim_1831","h_muslim_1854","h_muslim_1941","h_muslim_1943","h_muslim_1993","h_muslim_2029","h_muslim_2045","h_muslim_2101","h_muslim_2163","h_muslim_2331","h_muslim_2523","h_muslim_2748","h_muslim_3026","h_muslim_3089","h_muslim_3133","h_muslim_3139","h_muslim_3154","h_muslim_3260","h_muslim_3336","h_muslim_3337","h_muslim_3339","h_muslim_3359","h_muslim_3527","h_muslim_3540","h_muslim_3574","h_muslim_3702","h_muslim_3949","h_muslim_4058","h_muslim_4074","h_muslim_4219","h_muslim_4260","h_muslim_4475","h_muslim_4613","h_muslim_4744","h_muslim_4792","h_muslim_4793","h_muslim_4909","h_nasai_313","h_nasai_452","h_nasai_627","h_nasai_630","h_nasai_783","h_nasai_1119","h_nasai_1166","h_nasai_1261","h_nasai_1262","h_nasai_1287","h_nasai_1342","h_nasai_1457","h_nasai_1818","h_nasai_1821","h_nasai_1822","h_nasai_1968","h_nasai_2360","h_nasai_2375","h_nasai_2477","h_nasai_2676","h_nasai_2855","h_nasai_2861","h_nasai_2905","h_nasai_2945","h_nasai_3039","h_nasai_3450","h_nasai_3627","h_nasai_3629","h_nasai_3924","h_nasai_3925","h_nasai_4060","h_nasai_4063","h_nasai_4129","h_nasai_4283","h_nasai_4299","h_tirmidzi_182","h_tirmidzi_213","h_tirmidzi_278","h_tirmidzi_295","h_tirmidzi_445","h_tirmidzi_562","h_tirmidzi_809","h_tirmidzi_897","h_tirmidzi_934","h_tirmidzi_973","h_tirmidzi_1001","h_tirmidzi_1129","h_tirmidzi_1726","h_tirmidzi_1802","h_tirmidzi_2059","h_tirmidzi_2109","h_tirmidzi_2183","h_tirmidzi_2249","h_tirmidzi_2421","h_tirmidzi_2474","h_tirmidzi_2547","h_tirmidzi_2838","h_tirmidzi_3348","h_tirmidzi_3530","h_tirmidzi_3532","q_12_8","q_12_14","q_56_85","q_9_52","h_abu-dawud_70","h_abu-dawud_193","h_abu-dawud_199","h_abu-dawud_210","h_abu-dawud_400","h_abu-dawud_594","h_abu-dawud_603","h_abu-dawud_693","h_abu-dawud_694","h_abu-dawud_746","h_abu-dawud_979","h_abu-dawud_1071","h_abu-dawud_1215","h_abu-dawud_1499","h_abu-dawud_1507","h_abu-dawud_1576","h_abu-dawud_1604","h_abu-dawud_1609","h_abu-dawud_2023","h_abu-dawud_2038","h_abu-dawud_2095","h_abu-dawud_2525","h_abu-dawud_2650","h_abu-dawud_2688","h_abu-dawud_2692","h_abu-dawud_2770","h_abu-dawud_3064","h_abu-dawud_3264","h_abu-dawud_3401","h_abu-dawud_3435","h_abu-dawud_3452","h_abu-dawud_3738","h_abu-dawud_4247","h_abu-dawud_4267","h_abu-dawud_4282","h_abu-dawud_4387","h_ahmad_8","h_ahmad_18","h_ahmad_42","h_ahmad_49","h_ahmad_134","h_ahmad_310","h_ahmad_386","h_ahmad_389","h_ahmad_403","h_ahmad_451","h_ahmad_517","h_ahmad_659","h_ahmad_784","h_ahmad_803","h_ahmad_813","h_ahmad_876","h_ahmad_893","h_ahmad_894","h_ahmad_897","h_ahmad_899","h_ahmad_900","h_ahmad_1031","h_ahmad_1152","h_ahmad_1211","h_ahmad_1249","h_ahmad_1250","h_ahmad_1418","h_ahmad_1480","h_ahmad_1485","h_ahmad_1532","h_ahmad_1605","h_ahmad_1606","h_ahmad_1645","h_ahmad_1648","h_ahmad_1650","h_ahmad_1839","h_ahmad_1850","h_ahmad_1933","h_ahmad_1987","h_ahmad_2153","h_ahmad_2501","h_ahmad_2663","h_ahmad_2722","h_ahmad_2744","h_ahmad_2801","h_ahmad_2860","h_ahmad_2889","h_ahmad_3270","h_ahmad_3319","h_ahmad_3579","h_ahmad_3653","h_ahmad_3656","h_ahmad_3678","h_ahmad_3715","h_ahmad_4107","h_ahmad_4267","h_ahmad_4271","q_15_23","h_bukhari_6","h_bukhari_58","h_bukhari_94","h_bukhari_524","h_bukhari_595","h_bukhari_644","h_bukhari_1014","h_bukhari_1176","h_bukhari_1178","h_bukhari_1182","h_bukhari_1188","h_bukhari_1236","h_bukhari_1450","h_bukhari_1468","h_bukhari_1546","h_bukhari_1669","h_bukhari_1695","h_bukhari_1817","h_bukhari_1922","h_bukhari_2723","h_bukhari_2761","h_bukhari_2832","h_bukhari_2903","h_bukhari_2907","h_bukhari_3240","h_bukhari_3359","h_bukhari_3423","h_bukhari_3430","h_bukhari_3459","h_bukhari_3476","h_bukhari_3479","h_bukhari_3570","h_bukhari_3585","h_bukhari_3602","h_bukhari_3621","h_bukhari_3686","h_bukhari_3883","h_bukhari_3891","h_bukhari_3910","h_bukhari_3937","h_bukhari_3938","h_bukhari_3969","h_bukhari_4021","h_bukhari_4182","h_bukhari_4214","h_bukhari_4227","h_bukhari_4315","h_bukhari_4721","h_bukhari_4782","h_bukhari_4804","h_bukhari_5034","h_bukhari_5244","h_bukhari_5345","h_bukhari_5396","h_bukhari_5630","h_bukhari_5834","h_bukhari_6339","h_bukhari_6371","h_bukhari_6533","h_darimi_26","h_darimi_53","h_darimi_75","h_darimi_415","h_darimi_463","h_darimi_781","h_darimi_798","h_darimi_845","h_darimi_872","h_darimi_942","h_darimi_1401","h_darimi_1449","h_darimi_1488","h_darimi_1525","h_darimi_1575","h_darimi_1588","h_darimi_1680","h_darimi_1990","h_darimi_2195","h_darimi_2692","h_darimi_2703","h_ibnu-majah_5","h_ibnu-majah_57","h_ibnu-majah_507","h_ibnu-majah_616","h_ibnu-majah_668","h_ibnu-majah_967","h_ibnu-majah_1415","h_ibnu-majah_1602","h_ibnu-majah_1783","h_ibnu-majah_2611","h_ibnu-majah_2756","h_ibnu-majah_2891","h_ibnu-majah_3093","h_ibnu-majah_3148","h_ibnu-majah_3227","h_ibnu-majah_3228","h_ibnu-majah_3257","h_ibnu-majah_3517","h_ibnu-majah_3655","h_ibnu-majah_3927","h_ibnu-majah_3982","h_ibnu-majah_3993","h_ibnu-majah_4000","h_ibnu-majah_4007","h_ibnu-majah_4078","h_ibnu-majah_4110","h_ibnu-majah_4111","h_ibnu-majah_4155","h_ibnu-majah_4196"],"ونحن له":["q_29_46","q_3_84","q_2_133","q_2_136","q_2_138","q_2_139"],"ونحمل":["h_malik_36","h_nasai_59","h_nasai_329","h_tirmidzi_64","h_abu-dawud_76","h_darimi_489","h_darimi_1573","h_ibnu-majah_348"],"ونحمل معنا":["h_malik_36","h_nasai_59","h_nasai_329","h_tirmidzi_64","h_abu-dawud_76","h_darimi_489","h_darimi_1573","h_ibnu-majah_348"],"ونحن نصلي":["h_malik_166","h_abu-dawud_1071","h_bukhari_1922"],"ونحن بذات":["h_malik_304","h_muslim_1728"],"ونحن محرمات":["h_malik_629"],"ونحن مع":["h_malik_629","h_muslim_1412","h_nasai_2861","h_abu-dawud_210","h_abu-dawud_1499","h_abu-dawud_2650","h_abu-dawud_2692","h_abu-dawud_3401","h_abu-dawud_4267","h_ahmad_1850","h_bukhari_1188","h_bukhari_3423","h_bukhari_4182","h_bukhari_4214","h_ibnu-majah_507","h_ibnu-majah_3148","h_ibnu-majah_3517"],"ونحر":["h_malik_777","h_malik_814","h_muslim_2013","h_muslim_2145","h_muslim_2147","h_nasai_2594","h_nasai_4127","h_abu-dawud_1470","h_bukhari_1450","h_bukhari_1578","h_bukhari_1593","h_bukhari_1599","h_bukhari_1681","h_ibnu-majah_3032"],"ونحر غيره":["h_malik_777"],"ونحر هديا":["h_malik_814"],"ونحن نذكر":["h_malik_820","h_ibnu-majah_5"],"ونحن محرمان":["h_malik_823"],"ونحو":["h_malik_961","h_tirmidzi_121","h_tirmidzi_1151","h_tirmidzi_1188","h_tirmidzi_1207","h_ibnu-majah_1550"],"ونحو هذا":["h_malik_961","h_tirmidzi_1188","h_tirmidzi_1207","h_ibnu-majah_1550"],"ونحن نرثهم":["h_malik_1274"],"ونحبه":["h_malik_1375","h_malik_1382","h_muslim_2271","h_muslim_2304","h_muslim_2305","h_muslim_2306","h_muslim_3911","h_tirmidzi_3593","h_ahmad_545","h_ahmad_3485","h_bukhari_1387","h_bukhari_2675","h_bukhari_2679","h_bukhari_3571","h_bukhari_3572","h_bukhari_3783","h_bukhari_4700","h_bukhari_5581","h_ibnu-majah_3071"],"ونحبه اللهم":["h_malik_1375","h_tirmidzi_3593","h_bukhari_3572"],"ونحن اغنياۤء":["q_3_181"],"ونحن نسبح":["q_2_30"],"ونحن احق":["q_2_247"],"ونحن نسمع":["h_muslim_13","h_tirmidzi_3348","h_ahmad_3678"],"ونحن ما":["h_muslim_212","h_ibnu-majah_3982"],"ونحن لا":["h_muslim_536","h_nasai_1287","h_ibnu-majah_4196"],"ونحن سألناه":["h_muslim_593"],"ونحن في":["h_muslim_601","h_muslim_624","h_muslim_1255","h_muslim_1511","h_muslim_3359","h_muslim_4058","h_muslim_4909","h_nasai_2360","h_nasai_2855","h_nasai_3629","h_abu-dawud_603","h_abu-dawud_1215","h_abu-dawud_1609","h_abu-dawud_4247","h_ahmad_8","h_ahmad_389","h_ahmad_876","h_ahmad_893","h_ahmad_1031","h_ahmad_1211","h_ahmad_1250","h_ahmad_1480","h_ahmad_2889","h_ahmad_3715","h_ahmad_4267","h_bukhari_3891","h_bukhari_6339","h_darimi_75","h_darimi_845"],"ونحن نحب":["h_muslim_958"],"ونحن شببة":["h_muslim_1047","h_nasai_630","h_ahmad_517","h_ahmad_2663","h_bukhari_595","h_bukhari_644","h_bukhari_5244","h_bukhari_6371","h_darimi_872"],"ونحن أربعون":["h_muslim_1061","h_ahmad_1605","h_ahmad_1606"],"ونحن السابقون":["h_muslim_1331","h_darimi_53"],"ونحن أول":["h_muslim_1332"],"ونحن بضعة":["h_muslim_1451"],"ونحن نغسل":["h_muslim_1471","h_muslim_1473","h_nasai_1818","h_nasai_1821","h_nasai_1822","h_ahmad_2860","h_ahmad_4107","h_bukhari_1176","h_bukhari_1182","h_ibnu-majah_1415"],"ونحن نمشي":["h_muslim_1518","h_tirmidzi_1802","h_ibnu-majah_3257"],"ونحن نتبعه":["h_muslim_1519","h_ahmad_813"],"ونحن ننظر":["h_muslim_1568"],"ونحن بشر":["h_muslim_1670"],"ونحن صيام":["h_muslim_1790"],"ونحن بها":["h_muslim_1797"],"ونحن جلوس":["h_muslim_1831","h_bukhari_3459","h_darimi_463"],"ونحن يومئذ":["h_muslim_1854","h_muslim_2029","h_bukhari_1669","h_darimi_26"],"ونحن محرمون":["h_muslim_1941","h_nasai_2676","h_ahmad_1987","h_bukhari_1695","h_ibnu-majah_2891"],"ونحن حرم":["h_muslim_1943","h_ahmad_42","h_ahmad_49"],"ونحن نقول":["h_muslim_1993","h_nasai_1261","h_nasai_1262","h_tirmidzi_445","h_bukhari_1468","h_darimi_2703"],"ونحر هديه":["h_muslim_2013","h_nasai_2594","h_bukhari_1578","h_bukhari_1681"],"ونحن نصرخ":["h_muslim_2045"],"ونحن بجمع":["h_muslim_2101"],"ونحر ثم":["h_muslim_2145"],"ونحر نسكه":["h_muslim_2147"],"ونحن بمنى":["h_muslim_2163","h_nasai_4299","h_abu-dawud_1609","h_darimi_1525"],"ونحبه فلما":["h_muslim_2271","h_bukhari_4700","h_bukhari_5581"],"ونحن شباب":["h_muslim_2331","h_tirmidzi_1001"],"ونحن حينئذ":["h_muslim_2523","h_muslim_3702"],"ونحن نبيع":["h_muslim_2748","h_nasai_3627","h_nasai_4283","h_ahmad_894"],"ونحملهما":["h_muslim_2978"],"ونحملهما ونخالف":["h_muslim_2978"],"ونحن أربع":["h_muslim_3026","h_muslim_3139"],"ونحن منه":["h_muslim_3089","h_bukhari_6","h_bukhari_3883"],"ونحن نحفر":["h_muslim_3133","h_bukhari_3359"],"ونحن ستة":["h_muslim_3154","h_bukhari_3602"],"ونحن نسرح":["h_muslim_3260","h_ibnu-majah_2756"],"ونحن ثلاث":["h_muslim_3336","h_muslim_3337","h_muslim_3339","h_nasai_4060","h_nasai_4063","h_abu-dawud_3264","h_bukhari_2761","h_ibnu-majah_4110"],"ونحن نأكل":["h_muslim_3527","h_tirmidzi_1726","h_ahmad_2801","h_bukhari_4721","h_darimi_1588","h_ibnu-majah_3227","h_ibnu-majah_3228"],"ونحن نجني":["h_muslim_3540"],"ونحن بأذربيجان":["h_muslim_3574","h_ahmad_18"],"ونحوه":["h_muslim_3733","h_abu-dawud_1381","h_abu-dawud_1484","h_bukhari_1606","h_bukhari_2438"],"ونحبه ثم":["h_muslim_3911","h_bukhari_2675","h_bukhari_2679"],"ونحن معه":["h_muslim_3949","h_muslim_4744","h_tirmidzi_278","h_ahmad_1152","h_bukhari_1236","h_bukhari_1450","h_darimi_1990"],"ونحن جميعا":["h_muslim_4074","h_bukhari_1817"],"ونحري":["h_muslim_4136","h_bukhari_1300","h_bukhari_2869"],"ونحوركما":["h_muslim_4214","h_bukhari_181","h_bukhari_3708"],"ونحوركما وأبشرا":["h_muslim_4214","h_bukhari_3708"],"ونحن باليمن":["h_muslim_4219","h_bukhari_2903","h_bukhari_3430"],"ونحن كنا":["h_muslim_4219","h_bukhari_524"],"ونحن غلمان":["h_muslim_4260","h_muslim_4475","h_ahmad_813","h_bukhari_5834"],"ونحمده":["h_muslim_4524","h_nasai_5070","h_tirmidzi_3130","h_tirmidzi_3164","h_ahmad_1322","h_darimi_967","h_darimi_2671"],"ونحمده على":["h_muslim_4524","h_nasai_5070","h_ahmad_1322"],"ونحن قعود":["h_muslim_4613","h_ibnu-majah_4078"],"ونحاها":["h_muslim_4790"],"ونحاها نحو":["h_muslim_4790"],"ونحن نتذاكر":["h_muslim_4792","h_tirmidzi_2109","h_ahmad_897","h_ahmad_900","h_ibnu-majah_3993","h_ibnu-majah_4007","h_ibnu-majah_4155"],"ونحن أسفل":["h_muslim_4793"],"ونحن تحتها":["h_muslim_4793","h_ahmad_899"],"ونحشر":["q_20_102"],"ونحشر المجرمين":["q_20_102"],"ونحشره":["q_20_124"],"ونحشره يوم":["q_20_124"],"ونحن نرعى":["h_nasai_313"],"ونحن ضلال":["h_nasai_452"],"ونحن عنه":["h_nasai_627","h_ibnu-majah_668"],"ونحن صفوف":["h_nasai_783"],"ونحوهما":["h_nasai_967","h_nasai_972","h_abu-dawud_669"],"ونحن حوله":["h_nasai_1119","h_tirmidzi_934","h_ahmad_3319","h_darimi_942"],"ونحمد":["h_nasai_1146","h_nasai_1325","h_bukhari_798"],"ونحمد ربنا":["h_nasai_1146"],"ونحن رافعو":["h_nasai_1166"],"ونحمد ثلاثا":["h_nasai_1325","h_bukhari_798"],"ونحن الآخرون":["h_nasai_1342"],"ونحن إذ":["h_nasai_1457"],"ونحن لكم":["h_nasai_1968"],"ونحن نفعلهقال":["h_nasai_2375"],"ونحن على":["h_nasai_2477","h_abu-dawud_2525","h_darimi_2195"],"ونحن بجمعسمعت":["h_nasai_2905"],"ونحن مشركون":["h_nasai_2945"],"ونحن نريد":["h_nasai_3039","h_nasai_3450","h_tirmidzi_182"],"ونحن تسعة":["h_nasai_3924","h_nasai_3925","h_tirmidzi_2183"],"ونحن مضطرون":["h_nasai_4063"],"ونحر بعضها":["h_nasai_4127"],"ونحن بالمدينة":["h_nasai_4129","h_bukhari_4782"],"ونحوا":["h_nasai_4225","h_tirmidzi_514","h_ahmad_676"],"ونحوا من":["h_nasai_4225","h_tirmidzi_514","h_ahmad_676"],"ونحتفر":["h_nasai_5044"],"ونحتفر الآبار":["h_nasai_5044"],"ونحترث":["h_nasai_5044"],"ونحترث البقول":["h_nasai_5044"],"ونحو ذلك":["h_tirmidzi_121","h_tirmidzi_1151","h_tirmidzi_1188"],"ونحن بالرقة":["h_tirmidzi_213"],"ونحى":["h_tirmidzi_250","h_abu-dawud_614"],"ونحى يديه":["h_tirmidzi_250","h_abu-dawud_614"],"ونحوها":["h_tirmidzi_284","h_abu-dawud_677","h_abu-dawud_3760","h_ahmad_2873","h_bukhari_5336","h_darimi_674"],"ونحوها من":["h_tirmidzi_284","h_abu-dawud_677"],"ونحن شبابقال":["h_tirmidzi_295"],"ونحن عنده":["h_tirmidzi_562","h_abu-dawud_2038","h_ahmad_134","h_ahmad_1418","h_ahmad_2744","h_ahmad_3270","h_bukhari_1014","h_bukhari_3969","h_bukhari_5345","h_darimi_415"],"ونحن وقوف":["h_tirmidzi_809"],"ونحن نستحب":["h_tirmidzi_897"],"ونحن بالأثرقال":["h_tirmidzi_973"],"ونحن نسمى":["h_tirmidzi_1129"],"ونحن قيامقال":["h_tirmidzi_1802"],"ونحن نتنازع":["h_tirmidzi_2059"],"ونحا":["h_tirmidzi_2118","h_ahmad_2537"],"ونحا بيده":["h_tirmidzi_2118","h_ahmad_2537"],"ونحن نعالج":["h_tirmidzi_2249","h_abu-dawud_4387","h_ibnu-majah_4111"],"ونحن الناعمات":["h_tirmidzi_2421"],"ونحن الراضيات":["h_tirmidzi_2421"],"ونحن نسير":["h_tirmidzi_2474","h_ibnu-majah_3927"],"ونحن رفقة":["h_tirmidzi_2547"],"ونحن نعبد":["h_tirmidzi_2838"],"ونحمده لما":["h_tirmidzi_3130"],"ونحمده ثلاثا":["h_tirmidzi_3164","h_darimi_967"],"ونحن ننقل":["h_tirmidzi_3530","h_bukhari_3585","h_bukhari_5630"],"ونحن نرجو":["h_tirmidzi_3532"],"ونحاس":["q_55_35"],"ونحاس فلا":["q_55_35"],"ونحن عصبة":["q_12_8","q_12_14"],"ونحفظ":["q_12_65"],"ونحفظ اخانا":["q_12_65"],"ونحيا":["q_23_37","q_45_24","h_bukhari_6493"],"ونحيا وما":["q_23_37","q_45_24"],"ونحن اقرب":["q_56_85"],"ونحن نتربص":["q_9_52"],"ونحن جنبان":["h_abu-dawud_70"],"ونحن صفوفوهذا":["h_abu-dawud_193"],"ونحن نفيض":["h_abu-dawud_199","h_darimi_781"],"ونحن عند":["h_abu-dawud_400","h_abu-dawud_1604","h_abu-dawud_3064","h_abu-dawud_3452","h_abu-dawud_3738","h_ahmad_1645","h_ahmad_1648","h_ahmad_1650","h_bukhari_5034"],"ونحن خلفه":["h_abu-dawud_594"],"ونحوهما من":["h_abu-dawud_669"],"ونحن نقرأ":["h_abu-dawud_693","h_ahmad_1532","h_ahmad_1839","h_ibnu-majah_4000"],"ونحن نقترئ":["h_abu-dawud_694"],"ونحن سجود":["h_abu-dawud_746"],"ونحن الفقراء":["h_abu-dawud_979"],"ونحوه فما":["h_abu-dawud_1381","h_bukhari_2438"],"ونحر رسول":["h_abu-dawud_1470"],"ونحوه من":["h_abu-dawud_1484"],"ونحن حلالان":["h_abu-dawud_1507","h_darimi_1401"],"ونحن بعرفة":["h_abu-dawud_1576"],"ونحرت":["h_abu-dawud_1588","h_abu-dawud_1589","h_bukhari_2717"],"ونحرت ها":["h_abu-dawud_1588","h_abu-dawud_1589"],"ونحن نصومه":["h_abu-dawud_2023","h_bukhari_3479"],"ونحن أيتام":["h_abu-dawud_2095"],"ونحلق":["h_abu-dawud_2395"],"ونحلق رأسه":["h_abu-dawud_2395"],"ونحن شهود":["h_abu-dawud_2688"],"ونحن نسعى":["h_abu-dawud_2688","h_darimi_1680"],"ونحن والله":["h_abu-dawud_2770"],"ونحن نصبغ":["h_abu-dawud_3435"],"ونحن ببيروت":["h_abu-dawud_4282"],"ونحن متنكبون":["h_ahmad_310"],"ونحن بخيبر":["h_ahmad_386"],"ونحن نفعله":["h_ahmad_403","h_ahmad_3653","h_ibnu-majah_1783"],"ونحن محاصروهم":["h_ahmad_451"],"ونحن نحوزها":["h_ahmad_659"],"ونحن ندعوهم":["h_ahmad_784"],"ونحن نبني":["h_ahmad_803"],"ونحن مرملون":["h_ahmad_1249"],"ونحن أربعة":["h_ahmad_1485"],"ونحن نزول":["h_ahmad_1933"],"ونحن بأرض":["h_ahmad_2153"],"ونحن بالبصرة":["h_ahmad_2501"],"ونحن بكابل":["h_ahmad_2722"],"ونحوها وفي":["h_ahmad_2873"],"ونحبه ألا":["h_ahmad_3485","h_bukhari_1387"],"ونحن سابع":["h_ahmad_3579"],"ونحن نفعلها":["h_ahmad_3656"],"ونحب":["h_ahmad_4158","h_bukhari_5788"],"ونحب أن":["h_ahmad_4158"],"ونحن نبكي":["h_ahmad_4271"],"ونحن الورثون":["q_15_23"],"ونحن نتوضأ":["h_bukhari_58","h_bukhari_94"],"ونحن نغسلها":["h_bukhari_1178"],"ونحته":["h_bukhari_1218"],"ونحته في":["h_bukhari_1218"],"ونحري ودفن":["h_bukhari_1300"],"ونحبه قال":["h_bukhari_1387"],"ونحر النبي":["h_bukhari_1450","h_bukhari_1599"],"ونحن أكثر":["h_bukhari_1546"],"ونحر ورأى":["h_bukhari_1593"],"ونحوه فقال":["h_bukhari_1606"],"ونحرت جزور":["h_bukhari_2717"],"ونحن الآن":["h_bukhari_2723"],"ونحن ألف":["h_bukhari_2832"],"ونحري وجمع":["h_bukhari_2869"],"ونحن وهم":["h_bukhari_2907"],"ونحن صغار":["h_bukhari_3240"],"ونحن نتبايع":["h_bukhari_3476"],"ونحن نبتغي":["h_bukhari_3570"],"ونحن نعد":["h_bukhari_3621"],"ونحن نقصر":["h_bukhari_3686"],"ونحن ننتظر":["h_bukhari_3910"],"ونحن داخلون":["h_bukhari_3937"],"ونحن معك":["h_bukhari_3938"],"ونحن أحق":["h_bukhari_4021"],"ونحن نتخوف":["h_bukhari_4227"],"ونحن ورثناه":["h_bukhari_4315"],"ونحن بمر":["h_bukhari_4804","h_darimi_1575"],"ونحن كذلك":["h_bukhari_5396"],"ونحب المال":["h_bukhari_5788"],"ونحل":["h_bukhari_6355"],"ونحل إلا":["h_bukhari_6355"],"ونحيا فإذا":["h_bukhari_6493"],"ونحن أحوج":["h_bukhari_6533"],"ونحوها للجنب":["h_darimi_674"],"ونحن جنب":["h_darimi_798"],"ونحن غاديان":["h_darimi_1449"],"ونحن نستره":["h_darimi_1488"],"ونحن قيام":["h_darimi_1680","h_ibnu-majah_3257"],"ونحمده في":["h_darimi_2671"],"ونحن أطفال":["h_darimi_2692"],"ونحشرهم":["q_17_97"],"ونحشرهم يوم":["q_17_97"],"ونحن فتيان":["h_ibnu-majah_57"],"ونحن نختضب":["h_ibnu-majah_616"],"ونحن ركوع":["h_ibnu-majah_967"],"ونحن متقدمون":["h_ibnu-majah_1602"],"ونحن بالطريق":["h_ibnu-majah_2611"],"ونحر علي":["h_ibnu-majah_3032"],"ونحبه وهو":["h_ibnu-majah_3071"],"ونحن بذي":["h_ibnu-majah_3093"],"ونحن صبيان":["h_ibnu-majah_3655"],"ونخل":["h_malik_1586","q_55_68","h_abu-dawud_371","q_26_148","h_bukhari_1964"],"ونخل وإن":["h_malik_1586"],"ونخالف":["h_muslim_2978"],"ونخالف بين":["h_muslim_2978"],"ونخاف":["h_muslim_4219","h_bukhari_1593"],"ونخاف وسأذكر":["h_muslim_4219"],"ونخزى":["q_20_134"],"ونخل ورمانۚ":["q_55_68"],"ونخيل":["q_13_4"],"ونخيل صنوان":["q_13_4"],"ونخل وقبور":["h_abu-dawud_371"],"ونخلع":["h_ahmad_134","h_ahmad_3270"],"ونخلع ما":["h_ahmad_134","h_ahmad_3270"],"ونخرجها":["h_ahmad_727"],"ونخرجها من":["h_ahmad_727"],"ونخرجها إذا":["h_ahmad_727"],"ونخر":["h_ahmad_3754"],"ونخر كأشد":["h_ahmad_3754"],"ونخدمهم":["h_ahmad_3866","h_bukhari_2670","h_bukhari_4942"],"ونخدمهم ونرد":["h_ahmad_3866","h_bukhari_2670","h_bukhari_4942"],"ونخل طلعها":["q_26_148"],"ونخلاۙ":["q_80_29"],"ونخاف أن":["h_bukhari_1593"],"ونخبر":["h_bukhari_6386"],"ونخبر به":["h_bukhari_6386"],"ونخزيهما":["h_bukhari_6618"],"ونخزيهما قال":["h_bukhari_6618"],"ونخلك":["h_darimi_32"],"ونخلك فعلت":["h_darimi_32"],"ونخرج":["q_17_13"],"ونخرج له":["q_17_13"],"ونخوفهمۙ":["q_17_60"],"ونخوفهمۙ فما":["q_17_60"],"ونخلا":["h_ibnu-majah_2431"],"ونخلا بالجوف":["h_ibnu-majah_2431"],"وندخلكم":["q_4_31"],"وندخلكم مدخلا":["q_4_31"],"وندخلهم":["q_4_57"],"وندخلهم ظلا":["q_4_57"],"ونداۤء":["q_2_171"],"ونداۤء ۗ":["q_2_171"],"وندعو":["h_muslim_23","h_nasai_4699","h_tirmidzi_2469","h_abu-dawud_3129","h_bukhari_492","h_bukhari_1311","h_bukhari_2864","h_bukhari_3742","h_bukhari_3743","h_bukhari_5403","h_bukhari_6631"],"وندعو إليه":["h_muslim_23","h_nasai_4699","h_tirmidzi_2469","h_abu-dawud_3129","h_bukhari_492","h_bukhari_1311","h_bukhari_2864"],"وندخل":["h_muslim_25","h_bukhari_51"],"وندخل به":["h_muslim_25","h_bukhari_51"],"وندر":["h_muslim_2391"],"وندر رسول":["h_muslim_2391"],"وندرت":["h_muslim_2391"],"وندرت فقام":["h_muslim_2391"],"وندع":["h_muslim_2974","h_muslim_4444","h_abu-dawud_2086","h_ahmad_1249","h_bukhari_1274","h_bukhari_1639","h_bukhari_4262","h_bukhari_4263"],"وندع ولدها":["h_muslim_2974"],"وندامة":["h_muslim_3171","h_tirmidzi_3131"],"وندامة إلا":["h_muslim_3171"],"وندع العمل":["h_muslim_4444","h_bukhari_1274","h_bukhari_4262","h_bukhari_4263"],"وندخره":["h_nasai_4136"],"وندامة و":["h_tirmidzi_3131"],"وندع الجهادقال":["h_abu-dawud_2086"],"وند":["h_abu-dawud_2373","h_bukhari_4774"],"وند بعير":["h_abu-dawud_2373","h_bukhari_4774"],"وندم":["h_ahmad_1159","h_bukhari_3969","h_bukhari_5074"],"وندم فقال":["h_ahmad_1159"],"وندع ديننا":["h_ahmad_1249"],"وندك":["h_ahmad_2230"],"وندك ابنتها":["h_ahmad_2230"],"ونداوي":["h_bukhari_927","h_bukhari_2669"],"ونداوي الكلمى":["h_bukhari_927"],"وندع قول":["h_bukhari_1639"],"وندعه":["h_bukhari_2529"],"وندعه فقال":["h_bukhari_2529"],"ونداوي الجرحى":["h_bukhari_2669"],"وندال":["h_bukhari_2723"],"وندال عليه":["h_bukhari_2723"],"وندعو به":["h_bukhari_3742","h_bukhari_5403"],"وندعو إليها":["h_bukhari_3743","h_bukhari_6631"],"وندم عمر":["h_bukhari_3969"],"وندم وقال":["h_bukhari_5074"],"ونذر":["q_19_72","h_muslim_4213","q_54_16","q_54_18","q_54_21","q_54_30","q_54_37","q_54_39","h_ahmad_4148","q_7_70","h_ibnu-majah_4231"],"ونذر الظلمين":["q_19_72"],"ونذيراۙ":["q_2_119","q_33_45","q_48_8"],"ونذيراۙ ولا":["q_2_119"],"ونذيراۚ":["q_41_4"],"ونذيراۚ فاعرض":["q_41_4"],"ونذهب":["h_muslim_1813","h_abu-dawud_2211"],"ونذهب إلى":["h_muslim_1813"],"ونذروا":["h_muslim_2868"],"ونذروا بها":["h_muslim_2868"],"ونذرت":["h_muslim_2868","h_darimi_2038"],"ونذرت لله":["h_muslim_2868"],"ونذر الظالمين":["h_muslim_4213","h_ahmad_4148","h_ibnu-majah_4231"],"ونذكرك":["q_20_34"],"ونذكرك كثيرا":["q_20_34"],"ونذيقه":["q_22_9"],"ونذيقه يوم":["q_22_9"],"ونذيرا":["q_34_28","q_35_24","h_abu-dawud_912","h_abu-dawud_1054","h_abu-dawud_1744","q_25_56","h_bukhari_1981","h_bukhari_4156","h_darimi_6"],"ونذيرا ولكن":["q_34_28"],"ونذيرا ۗوان":["q_35_24"],"ونذيرا بين":["h_abu-dawud_912","h_abu-dawud_1744"],"ونذيرا ولا":["h_abu-dawud_1054"],"ونذهب ولا":["h_abu-dawud_2211"],"ونذبح":["h_abu-dawud_2379"],"ونذبح البقرة":["h_abu-dawud_2379"],"ونذر ما":["q_7_70"],"ونذيرا وحرزا":["h_bukhari_1981","h_darimi_6"],"ونذيرا قال":["h_bukhari_4156"],"ونذرهم":["q_6_110"],"ونذرهم في":["q_6_110"],"ونذرت لئن":["h_darimi_2038"],"ونذيراۘ":["q_17_105"],"ونذير":["q_5_19"],"ونذير ۗوالله":["q_5_19"],"ونرى":["h_malik_893","h_muslim_3826"],"ونرى عليها":["h_malik_893"],"ونرثه":["q_19_80","h_bukhari_4061"],"ونرثه ما":["q_19_80","h_bukhari_4061"],"ونرد":["h_muslim_2054","h_ahmad_3866","h_bukhari_2669","h_bukhari_2670","h_bukhari_4942","q_6_71"],"ونرد عليه":["h_muslim_2054"],"ونرجع":["h_muslim_3105","h_ahmad_784","h_bukhari_4161"],"ونرجع ولما":["h_muslim_3105","h_ahmad_784","h_bukhari_4161"],"ونرفع":["h_muslim_3549","h_tirmidzi_2576","h_ahmad_3640"],"ونرفع للنبي":["h_muslim_3549"],"ونرى ذلك":["h_muslim_3826"],"ونرمي":["h_tirmidzi_849"],"ونرمي عن":["h_tirmidzi_849"],"ونرفع لرسول":["h_tirmidzi_2576","h_ahmad_3640"],"ونرويك":["h_tirmidzi_3110"],"ونرويك من":["h_tirmidzi_3110"],"ونرد الجرحى":["h_ahmad_3866","h_bukhari_2670"],"ونرد القتلى":["h_bukhari_2669","h_bukhari_4942"],"ونرد على":["q_6_71"],"ونرىه":["q_70_7"],"ونرىه قريباۗ":["q_70_7"],"ونريد":["q_28_5"],"ونريد ان":["q_28_5"],"ونري":["q_28_6"],"ونري فرعون":["q_28_6"],"ونزلنا":["q_50_9","q_20_80","h_abu-dawud_1489","h_bukhari_1458","q_16_89","h_darimi_1663"],"ونزلنا من":["q_50_9"],"ونزل":["h_muslim_173","h_muslim_1988","h_muslim_2394","h_muslim_2522","h_muslim_3099","h_muslim_4841","h_nasai_1484","h_nasai_2827","h_nasai_3107","h_nasai_4061","h_nasai_4946","h_tirmidzi_2844","h_tirmidzi_2869","h_tirmidzi_3008","h_tirmidzi_3170","h_abu-dawud_979","h_abu-dawud_2222","h_abu-dawud_2551","h_abu-dawud_3610","q_25_25","h_ahmad_2396","h_ahmad_2633","h_bukhari_56","h_bukhari_365","h_bukhari_654","h_bukhari_965","h_bukhari_3513","h_bukhari_3608","h_bukhari_3937","h_bukhari_4079","h_bukhari_4217","h_bukhari_4926","h_bukhari_6396","h_ibnu-majah_1584","h_ibnu-majah_3960","h_ibnu-majah_4005"],"ونزل يا":["h_muslim_173","h_abu-dawud_3610"],"ونزلت":["h_muslim_1349","h_muslim_2522","h_muslim_3283","h_muslim_4021","h_muslim_4042","h_muslim_4523","h_nasai_1963","h_nasai_2094","h_nasai_2374","h_nasai_3776","h_nasai_5078","h_tirmidzi_3008","h_tirmidzi_3062","h_tirmidzi_3102","h_tirmidzi_3129","h_tirmidzi_3478","h_abu-dawud_258","h_abu-dawud_602","h_abu-dawud_2439","h_abu-dawud_3683","h_ahmad_1987","h_ahmad_1988","h_ahmad_3973","h_bukhari_1782","h_bukhari_3438","h_bukhari_4084","h_bukhari_4131","h_bukhari_4206","h_bukhari_6411","h_ibnu-majah_189"],"ونزلت هذه":["h_muslim_1349","h_muslim_2522","h_muslim_3283","h_tirmidzi_3102","h_ahmad_1987","h_bukhari_4084"],"ونزل رسول":["h_muslim_1988","h_muslim_2522","h_nasai_1484","h_bukhari_3608"],"ونزل القرآن":["h_muslim_2394","h_nasai_2827","h_nasai_3107","h_tirmidzi_2869","h_bukhari_6396","h_ibnu-majah_4005"],"ونزل الحجاب":["h_muslim_2394"],"ونزلت فنزلت":["h_muslim_2522"],"ونزل الوحي":["h_muslim_3099"],"ونزلت يا":["h_muslim_4021","h_muslim_4042","h_bukhari_6411"],"ونزلت عليهم":["h_muslim_4523","h_tirmidzi_3129","h_ibnu-majah_189"],"ونزول":["h_muslim_4792","h_tirmidzi_598","h_tirmidzi_844","h_ahmad_897"],"ونزول عيسى":["h_muslim_4792","h_ahmad_897"],"ونزل يثرب":["h_muslim_4841"],"ونزلنا عليكم":["q_20_80"],"ونزلت إنك":["h_nasai_1963","h_bukhari_3438"],"ونزلت في":["h_nasai_2094","h_tirmidzi_3008","h_tirmidzi_3478"],"ونزلت الزكاة":["h_nasai_2374"],"ونزلت فيهم":["h_nasai_3776","h_abu-dawud_3683"],"ونزل في":["h_nasai_4061","h_tirmidzi_3008","h_ibnu-majah_1584"],"ونزل فجعل":["h_nasai_4946"],"ونزلت وركب":["h_nasai_5078"],"ونزول الرب":["h_tirmidzi_598"],"ونزول الأبطح":["h_tirmidzi_844"],"ونزل فيهم":["h_tirmidzi_2844","h_ibnu-majah_3960"],"ونزلت الآية":["h_tirmidzi_3062","h_ahmad_1988"],"ونزل الشهداء":["h_tirmidzi_3170"],"ونزداد":["q_12_65"],"ونزداد كيل":["q_12_65"],"ونزلت عن":["h_abu-dawud_258","h_ahmad_3973"],"ونزلت وتركنا":["h_abu-dawud_602"],"ونزل فصلى":["h_abu-dawud_979"],"ونزلنا فجلست":["h_abu-dawud_1489"],"ونزلهم":["h_abu-dawud_1603","h_ahmad_1170"],"ونزلهم منازلهم":["h_abu-dawud_1603","h_ahmad_1170"],"ونزع":["h_abu-dawud_1643","h_ahmad_416","q_26_33","q_7_108","h_bukhari_2751","h_ibnu-majah_4195"],"ونزع صاحبه":["h_abu-dawud_1643"],"ونزل إليهم":["h_abu-dawud_2222","h_bukhari_3513"],"ونزلت سورة":["h_abu-dawud_2439"],"ونزل من":["h_abu-dawud_2551"],"ونزل الملۤىكة":["q_25_25"],"ونزلوا":["h_ahmad_134","h_ahmad_1318","h_ahmad_3270"],"ونزلوا بلادي":["h_ahmad_134","h_ahmad_3270"],"ونزع البردة":["h_ahmad_416"],"ونزلوا فقال":["h_ahmad_1318"],"ونزلتي":["h_ahmad_2585","h_ahmad_2820"],"ونزلتي فلحقني":["h_ahmad_2585","h_ahmad_2820"],"ونزل النبي":["h_ahmad_2633"],"ونزعنا":["q_15_47","q_7_43","h_bukhari_5749","q_28_75"],"ونزعنا ما":["q_15_47","q_7_43","h_bukhari_5749"],"ونزع يده":["q_26_33","q_7_108"],"ونزل لتسع":["h_bukhari_365"],"ونزل بك":["h_bukhari_654"],"ونزل عن":["h_bukhari_965"],"ونزلنا معه":["h_bukhari_1458"],"ونزلت وكلوا":["h_bukhari_1782"],"ونزع ثنيته":["h_bukhari_2751"],"ونزل فثنى":["h_bukhari_3937"],"ونزل عذرك":["h_bukhari_4079"],"ونزلت قل":["h_bukhari_4131"],"ونزلت فيه":["h_bukhari_4206"],"ونزل هم":["h_bukhari_4217"],"ونزل فدعاهم":["h_bukhari_4926"],"ونزونا":["h_bukhari_5994"],"ونزونا على":["h_bukhari_5994"],"ونزلنا عليك":["q_16_89"],"ونزهه":["h_darimi_412"],"ونزهه أن":["h_darimi_412"],"ونزلنا بين":["h_darimi_1663"],"ونزلنه":["q_17_106"],"ونزلنه تنزيلا":["q_17_106"],"ونزعنا من":["q_28_75"],"ونزيد":["h_ibnu-majah_2212"],"ونزيد في":["h_ibnu-majah_2212"],"ونزع واستغفر":["h_ibnu-majah_4195"],"ونسي":["q_18_57","h_muslim_2891","h_muslim_4054","h_tirmidzi_2364","h_tirmidzi_2862","h_tirmidzi_2916","h_tirmidzi_3119","h_abu-dawud_3054","q_36_78","h_bukhari_3404","h_bukhari_4536"],"ونسي ما":["q_18_57"],"ونساۤء":["q_4_1","q_4_176","q_33_59","q_48_25"],"ونساۤء ۚ":["q_4_1"],"ونساۤء فللذكر":["q_4_176"],"ونسافر":["h_malik_576"],"ونسافر معه":["h_malik_576"],"ونستخبر":["h_malik_952"],"ونستخبر عنها":["h_malik_952"],"ونسوق":["q_19_86"],"ونسوق المجرمين":["q_19_86"],"ونساۤءنا":["q_3_61"],"ونساۤءنا ونساۤءكم":["q_3_61"],"ونساۤءكم":["q_3_61"],"ونساۤءكم وانفسنا":["q_3_61"],"ونسيت":["h_muslim_377","h_muslim_1203","h_muslim_2205","h_muslim_2207","h_muslim_3117","h_muslim_4089","h_nasai_521","h_nasai_526","h_nasai_2765","h_nasai_3810","h_nasai_4708","h_tirmidzi_2614","h_abu-dawud_49","h_abu-dawud_325","h_abu-dawud_1665","h_bukhari_508","h_bukhari_514","h_bukhari_564","h_bukhari_729","h_bukhari_2382","h_bukhari_2717","h_bukhari_2825","h_bukhari_3663","h_bukhari_3771","h_bukhari_4682","h_darimi_914","h_ibnu-majah_257","h_ibnu-majah_1941"],"ونسيت العاشرة":["h_muslim_377","h_nasai_4708","h_tirmidzi_2614","h_abu-dawud_49","h_ibnu-majah_257"],"ونستغفر":["h_muslim_381","h_tirmidzi_8","h_abu-dawud_8","h_bukhari_380","h_darimi_430"],"ونستغفر الله":["h_muslim_381","h_tirmidzi_8","h_abu-dawud_8","h_bukhari_380","h_darimi_430"],"ونسجد":["h_muslim_872","h_abu-dawud_1174","h_bukhari_1013","h_bukhari_1014","h_bukhari_1017"],"ونسجد معه":["h_muslim_872","h_abu-dawud_1174","h_bukhari_1014","h_bukhari_1017"],"ونسبا":["h_muslim_974"],"ونسبا أبا":["h_muslim_974"],"ونسيت ما":["h_muslim_1203","h_nasai_521","h_nasai_526","h_bukhari_508","h_bukhari_514","h_bukhari_564","h_bukhari_729","h_darimi_914"],"ونسكي":["h_muslim_1209","h_nasai_885","h_nasai_886","h_nasai_887","h_tirmidzi_3172","h_tirmidzi_3173","h_tirmidzi_3174","h_abu-dawud_636","h_abu-dawud_2348","q_6_162","h_darimi_857","h_darimi_1511","h_ibnu-majah_3077"],"ونسكي ومحياي":["h_muslim_1209","h_nasai_885","h_nasai_886","h_nasai_887","h_tirmidzi_3172","h_tirmidzi_3173","h_tirmidzi_3174","h_abu-dawud_636","h_abu-dawud_2348","q_6_162","h_darimi_857","h_darimi_1511","h_ibnu-majah_3077"],"ونستعينه":["h_muslim_1355","h_nasai_3134","h_darimi_1750","h_ibnu-majah_1847","h_ibnu-majah_1848"],"ونستعينه من":["h_muslim_1355","h_nasai_3134"],"ونساؤه":["h_muslim_1991","h_nasai_2665","h_bukhari_1459"],"ونساؤه لم":["h_muslim_1991","h_nasai_2665","h_bukhari_1459"],"ونسيت أن":["h_muslim_2205","h_muslim_2207","h_nasai_2765","h_abu-dawud_1665","h_bukhari_3771"],"ونسي فلم":["h_muslim_2891"],"ونستعين":["h_muslim_3109"],"ونستعين الله":["h_muslim_3109"],"ونسيت السابع":["h_muslim_3117"],"ونسبه":["h_muslim_3131","h_muslim_3795","h_muslim_4051","h_abu-dawud_1313","h_abu-dawud_4065","h_bukhari_3087","h_bukhari_3104","h_bukhari_6615"],"ونسبه غير":["h_muslim_3131"],"ونسوة":["h_muslim_3142","h_tirmidzi_1500","h_abu-dawud_2104"],"ونسوة من":["h_muslim_3142","h_abu-dawud_2104"],"ونسك":["h_muslim_3380","h_nasai_1531","h_nasai_4102","h_nasai_4103","h_abu-dawud_2353","h_bukhari_902","h_bukhari_930"],"ونسك نسكنا":["h_muslim_3380","h_nasai_1531","h_nasai_4102","h_nasai_4103","h_abu-dawud_2353","h_bukhari_902","h_bukhari_930"],"ونساء":["h_muslim_3666","h_muslim_4224","h_nasai_1378","h_nasai_2422","h_nasai_3309","h_abu-dawud_2592","h_abu-dawud_2600","h_ahmad_3893","h_bukhari_1297","h_bukhari_4499","h_bukhari_6191"],"ونساء كاسيات":["h_muslim_3666"],"ونسبه ابن":["h_muslim_3795"],"ونسبه إلى":["h_muslim_4051","h_abu-dawud_1313","h_bukhari_3087","h_bukhari_3104","h_bukhari_6615"],"ونسي صاحب":["h_muslim_4054","h_tirmidzi_2916"],"ونسيت بعض":["h_muslim_4089"],"ونسقك":["h_muslim_4096"],"ونسقك خمرا":["h_muslim_4096"],"ونساء مقبلين":["h_muslim_4224"],"ونسيه":["h_muslim_4777","h_tirmidzi_2117","h_abu-dawud_3588","h_ahmad_2215","h_ahmad_3432","h_bukhari_2953"],"ونسيه من":["h_muslim_4777","h_tirmidzi_2117","h_abu-dawud_3588","h_ahmad_3432","h_bukhari_2953"],"ونسيته":["h_nasai_430"],"ونسيته سأله":["h_nasai_430"],"ونسجدها":["h_nasai_946"],"ونسجدها شكرا":["h_nasai_946"],"ونسلم":["h_nasai_1260","h_bukhari_5474"],"ونسلم أما":["h_nasai_1260"],"ونسائه":["h_nasai_1338"],"ونسائه وحشد":["h_nasai_1338"],"ونستغفره":["h_nasai_1378","h_nasai_3133","h_tirmidzi_1023","h_abu-dawud_912","h_abu-dawud_1744","h_bukhari_3681","h_bukhari_4283","h_darimi_1750","h_ibnu-majah_1847"],"ونستغفره ونعوذ":["h_nasai_1378","h_nasai_3133","h_tirmidzi_1023","h_abu-dawud_912","h_abu-dawud_1744","h_darimi_1750","h_ibnu-majah_1847"],"ونساء واتقوا":["h_nasai_1378","h_nasai_2422"],"ونساءه":["h_nasai_1555","h_tirmidzi_734","h_abu-dawud_1138","h_darimi_1359","h_ibnu-majah_1266"],"ونساءه حتى":["h_nasai_1555"],"ونساء النبي":["h_nasai_3309","h_bukhari_4499"],"ونسخ":["h_nasai_3387","h_abu-dawud_1888"],"ونسخ أجل":["h_nasai_3387","h_abu-dawud_1888"],"ونسيت الذي":["h_nasai_3810"],"ونسفه":["h_nasai_4063"],"ونسفه ثم":["h_nasai_4063"],"ونسمي":["h_nasai_4171","h_bukhari_1127"],"ونسمي أنفسنا":["h_nasai_4171"],"ونسيح":["h_nasai_5044"],"ونسيح كما":["h_nasai_5044"],"ونساءه فقام":["h_tirmidzi_734"],"ونسيئة":["h_tirmidzi_1152","h_bukhari_2317"],"ونسيئة بعشرين":["h_tirmidzi_1152"],"ونسوة معها":["h_tirmidzi_1500"],"ونسي الكبير":["h_tirmidzi_2364"],"ونسي الجبار":["h_tirmidzi_2364"],"ونسي المقابر":["h_tirmidzi_2364"],"ونسي المبتدا":["h_tirmidzi_2364"],"ونساءنا":["h_tirmidzi_2824","h_tirmidzi_3416","h_bukhari_2134"],"ونساءنا ونساءكم":["h_tirmidzi_2824","h_tirmidzi_3416"],"ونساءكم":["h_tirmidzi_2824","h_tirmidzi_3416"],"ونساءكم الآية":["h_tirmidzi_2824","h_tirmidzi_3416"],"ونسي آدم":["h_tirmidzi_2862"],"ونسي فنسيت":["h_tirmidzi_3119"],"ونسمع":["h_tirmidzi_3482","h_ahmad_1444"],"ونسمع منه":["h_tirmidzi_3482"],"ونساۤء المؤمنين":["q_33_59"],"ونسيت المغرب":["h_abu-dawud_325"],"ونسبح":["h_abu-dawud_696"],"ونسبح ركوعا":["h_abu-dawud_696"],"ونسأل":["h_abu-dawud_912"],"ونسأل الله":["h_abu-dawud_912"],"ونسوا":["h_abu-dawud_1055","q_5_13"],"ونساءه والناس":["h_abu-dawud_1138","h_darimi_1359"],"ونسائهم":["h_abu-dawud_2233"],"ونسائهم فقال":["h_abu-dawud_2233"],"ونسقي":["h_abu-dawud_2288","h_ahmad_3202","h_ahmad_3932","h_bukhari_5336"],"ونسقي السويق":["h_abu-dawud_2288","h_ahmad_3932"],"ونستبيح":["h_abu-dawud_2541"],"ونستبيح نساءكم":["h_abu-dawud_2541"],"ونساء بني":["h_abu-dawud_2592"],"ونساء من":["h_abu-dawud_2600","h_ahmad_3893"],"ونسي بعض":["h_abu-dawud_3054"],"ونستشفع":["h_abu-dawud_3948"],"ونستشفع بالله":["h_abu-dawud_3948"],"ونسبه لنا":["h_abu-dawud_4065"],"ونسقيه":["q_25_49"],"ونسقيه مما":["q_25_49"],"ونسي خلقهۗ":["q_36_78"],"ونسوهۗ":["q_58_6"],"ونسوهۗ والله":["q_58_6"],"ونسيء":["h_ahmad_134"],"ونسيء الجوار":["h_ahmad_134"],"ونستهزئ":["h_ahmad_310"],"ونستهزئ به":["h_ahmad_310"],"ونسيتهما":["h_ahmad_1249"],"ونسيتهما وكتبت":["h_ahmad_1249"],"ونسمع رجع":["h_ahmad_1444"],"ونسيه عمر":["h_ahmad_2215"],"ونسقي الناس":["h_ahmad_3202"],"ونسيئ":["h_ahmad_3270"],"ونسيئ الجوار":["h_ahmad_3270"],"ونساۤء مؤمنت":["q_48_25"],"ونستحي":["q_7_127"],"ونستحي نساۤءهمۚ":["q_7_127"],"ونسجد حتى":["h_bukhari_1013"],"ونسمي ويسلم":["h_bukhari_1127"],"ونساء عراة":["h_bukhari_1297","h_bukhari_6191"],"ونساء وصبيان":["h_bukhari_1297"],"ونساءنا قال":["h_bukhari_2134"],"ونساءنا فأته":["h_bukhari_2134"],"ونسيئة فجاءنا":["h_bukhari_2317"],"ونسيت السوط":["h_bukhari_2382","h_bukhari_4682"],"ونسيت السابعقال":["h_bukhari_2717"],"ونسيت الثالثةوقال":["h_bukhari_2825"],"ونسي الثالثة":["h_bukhari_3404"],"ونسيت بقيتهم":["h_bukhari_3663"],"ونستغفره إذا":["h_bukhari_3681","h_bukhari_4283"],"ونسبها":["h_bukhari_4397","h_bukhari_4439"],"ونسبها وسنتها":["h_bukhari_4397"],"ونسبها والصداق":["h_bukhari_4439"],"ونسي فأطاف":["h_bukhari_4536"],"ونسقي بنواضحنا":["h_bukhari_5336"],"ونسلم عليها":["h_bukhari_5474"],"ونستعينه ونستغفره":["h_darimi_1750","h_ibnu-majah_1847"],"ونسوا حظا":["q_5_13"],"ونسراۚ":["q_71_23"],"ونسينا":["h_ibnu-majah_23"],"ونسينا والحديث":["h_ibnu-majah_23"],"ونستنجي":["h_ibnu-majah_317"],"ونستنجي بالماء":["h_ibnu-majah_317"],"ونساءه في":["h_ibnu-majah_1266"],"ونستعينه ونعوذ":["h_ibnu-majah_1848"],"ونسيت الثالثةحدثنا":["h_ibnu-majah_1941"],"ونشا":["h_muslim_2382","h_darimi_1747","h_ibnu-majah_1841"],"ونشا قالت":["h_muslim_2382"],"ونشتري":["h_muslim_2750"],"ونشتري الذهب":["h_muslim_2750"],"ونشتهيه":["h_muslim_4690"],"ونشتهيه ولوددنا":["h_muslim_4690"],"ونش":["h_nasai_3203","h_abu-dawud_1735"],"ونش وذلك":["h_nasai_3203"],"ونشرب":["h_nasai_4063","h_nasai_5044","h_tirmidzi_1484","h_tirmidzi_1719","h_tirmidzi_1802","h_ibnu-majah_3257"],"ونشرب عليها":["h_nasai_4063"],"ونشترك":["h_nasai_4101"],"ونشترك فيها":["h_nasai_4101"],"ونشرب كما":["h_nasai_5044"],"ونشرب في":["h_tirmidzi_1484","h_tirmidzi_1719"],"ونشرب ونحن":["h_tirmidzi_1802","h_ibnu-majah_3257"],"ونشابهم":["h_tirmidzi_2166","h_ibnu-majah_4028"],"ونشابهم وجعابهم":["h_tirmidzi_2166"],"ونش فقلت":["h_abu-dawud_1735"],"ونشئا":["h_ahmad_830"],"ونشئا يتخذون":["h_ahmad_830"],"ونشر":["h_ahmad_2523"],"ونشر أصابع":["h_ahmad_2523"],"ونشرككم":["h_bukhari_2157","h_bukhari_2518"],"ونشرككم في":["h_bukhari_2157","h_bukhari_2518"],"ونشا وقالت":["h_darimi_1747"],"ونشره":["h_ibnu-majah_206"],"ونشره وولدا":["h_ibnu-majah_206"],"ونشا هل":["h_ibnu-majah_1841"],"ونشابهم وأترستهم":["h_ibnu-majah_4028"],"ونصله":["q_4_115"],"ونصله جهنمۗ":["q_4_115"],"ونصفها":["h_malik_173","h_muslim_586","h_nasai_899","h_tirmidzi_2808","h_abu-dawud_686","h_ibnu-majah_3739"],"ونصفها لعبدي":["h_malik_173","h_muslim_586","h_nasai_899","h_tirmidzi_2808","h_abu-dawud_686","h_ibnu-majah_3739"],"ونصفه":["h_malik_502","q_73_20","h_muslim_3544","h_muslim_4597"],"ونصفه في":["h_malik_502","h_muslim_4597"],"ونصر":["h_malik_833","h_muslim_1163","h_muslim_1994","h_muslim_2239","h_muslim_3566","h_nasai_3608","h_nasai_4501","h_tirmidzi_224","h_tirmidzi_713","h_tirmidzi_798","h_tirmidzi_873","h_tirmidzi_966","h_tirmidzi_1598","h_tirmidzi_1715","h_tirmidzi_1832","h_tirmidzi_2043","h_tirmidzi_2335","h_tirmidzi_2577","h_tirmidzi_2666","h_abu-dawud_1123","h_abu-dawud_1565","h_abu-dawud_1845","h_abu-dawud_2324","h_abu-dawud_3819","h_ahmad_317","h_ahmad_3464","h_bukhari_1163","h_bukhari_1670","h_bukhari_2265","h_bukhari_2773","h_bukhari_2854","h_bukhari_4472","h_bukhari_4899","h_bukhari_5109","h_bukhari_5449","h_bukhari_5461","h_bukhari_5601","h_darimi_1425","h_ibnu-majah_1352","h_ibnu-majah_2209","h_ibnu-majah_2583","h_ibnu-majah_3030","h_ibnu-majah_3175","h_ibnu-majah_3228","h_ibnu-majah_4017"],"ونصر عبده":["h_malik_833","h_muslim_1994","h_muslim_2239","h_nasai_4501","h_tirmidzi_873","h_abu-dawud_1565","h_abu-dawud_2324","h_abu-dawud_3819","h_ahmad_317","h_ahmad_3464","h_bukhari_1670","h_bukhari_2773","h_bukhari_2854","h_bukhari_5601","h_darimi_1425","h_ibnu-majah_2583","h_ibnu-majah_3030"],"ونصف":["h_malik_1156","h_malik_1188","h_malik_1218","h_muslim_3357","h_nasai_2170","h_nasai_2171","h_nasai_2172","h_nasai_2173","h_nasai_2174","h_nasai_2179","h_ahmad_39","h_bukhari_2897","h_bukhari_3666","h_bukhari_6387","h_darimi_1224","h_darimi_1297","h_darimi_2478","h_darimi_2649"],"ونصف درهم":["h_malik_1156"],"ونصف ربحه":["h_malik_1188"],"ونصف شهر":["h_malik_1218"],"ونصفه وثلثه":["q_73_20"],"ونصب":["h_muslim_13","h_nasai_1142","h_nasai_1237","h_nasai_1240","h_nasai_2019","h_tirmidzi_257","h_tirmidzi_269","h_tirmidzi_562","h_abu-dawud_614","h_abu-dawud_811","h_bukhari_471","h_bukhari_785","h_darimi_415","h_darimi_952"],"ونصب هذه":["h_muslim_13"],"ونصرت":["h_muslim_789","h_muslim_791","h_muslim_792","h_nasai_2946","h_nasai_2947","h_tirmidzi_1474","h_bukhari_2755","h_bukhari_6149","h_bukhari_6162","h_bukhari_6393","h_darimi_2003"],"ونصرت بالرعب":["h_muslim_789","h_muslim_791","h_muslim_792","h_nasai_2946","h_nasai_2947","h_tirmidzi_1474","h_bukhari_2755","h_bukhari_6149","h_bukhari_6162","h_bukhari_6393","h_darimi_2003"],"ونصيحته":["h_muslim_1019","h_bukhari_407","h_bukhari_4677"],"ونصيحته للمنافقين":["h_muslim_1019"],"ونصر بن":["h_muslim_1163","h_tirmidzi_224","h_tirmidzi_713","h_tirmidzi_798","h_tirmidzi_966","h_tirmidzi_1598","h_tirmidzi_1715","h_tirmidzi_1832","h_tirmidzi_2043","h_tirmidzi_2335","h_tirmidzi_2577","h_abu-dawud_1123","h_abu-dawud_1845","h_ibnu-majah_1352","h_ibnu-majah_2209","h_ibnu-majah_3175","h_ibnu-majah_3228","h_ibnu-majah_4017"],"ونصبها":["h_muslim_1493","h_nasai_1860"],"ونصبها إلى":["h_muslim_1493"],"ونصيب":["h_muslim_1698","h_muslim_3089","h_bukhari_3883","h_darimi_412"],"ونصيب كما":["h_muslim_1698"],"ونصوم":["h_muslim_1813","h_abu-dawud_1989","h_bukhari_1824"],"ونصوم صبياننا":["h_muslim_1813","h_bukhari_1824"],"ونصنع":["h_muslim_1813"],"ونصنع لهم":["h_muslim_1813"],"ونصحت":["h_muslim_1994","h_abu-dawud_1565","q_7_79","q_7_93","h_darimi_1425","h_ibnu-majah_3030"],"ونصحت فقال":["h_muslim_1994","h_darimi_1425","h_ibnu-majah_3030"],"ونصحبه":["h_muslim_2742"],"ونصحبه فلم":["h_muslim_2742"],"ونصيب منه":["h_muslim_3089","h_bukhari_3883"],"ونصف فلم":["h_muslim_3357","h_bukhari_6387"],"ونصفه بين":["h_muslim_3544"],"ونصر المظلوم":["h_muslim_3566","h_nasai_3608","h_tirmidzi_2666","h_bukhari_1163","h_bukhari_2265","h_bukhari_4472","h_bukhari_4899","h_bukhari_5109","h_bukhari_5449"],"ونصارى":["h_muslim_4620"],"ونصارى العرب":["h_muslim_4620"],"ونصير":["h_nasai_169","h_abu-dawud_3681"],"ونصير بن":["h_nasai_169","h_abu-dawud_3681"],"ونصب اليمنى":["h_nasai_1142","h_nasai_1237","h_nasai_1240","h_abu-dawud_614","h_abu-dawud_811","h_bukhari_785"],"ونصب أصبعه":["h_nasai_1142"],"ونصبها وأذاها":["h_nasai_1860"],"ونصرة":["h_nasai_1868"],"ونصرة المظلوم":["h_nasai_1868"],"ونصب فيها":["h_nasai_2019"],"ونصف الصلاة":["h_nasai_2170","h_nasai_2171","h_nasai_2173","h_nasai_2179","h_darimi_1297"],"ونصف الصلاةأخبرنا":["h_nasai_2172","h_nasai_2174"],"ونصبوا":["h_nasai_4007","h_bukhari_2308"],"ونصبوا القدور":["h_nasai_4007","h_bukhari_2308"],"ونصرنه":["q_21_77"],"ونصرنه من":["q_21_77"],"ونصب القدمينقال":["h_tirmidzi_257"],"ونصب القدمين":["h_tirmidzi_257"],"ونصب رجله":["h_tirmidzi_269"],"ونصب الجبال":["h_tirmidzi_562","h_darimi_415"],"ونصح":["h_tirmidzi_1566"],"ونصح لمواليهقال":["h_tirmidzi_1566"],"ونصلح":["h_abu-dawud_373"],"ونصلح صنعتها":["h_abu-dawud_373"],"ونصب قدمه":["h_abu-dawud_614","h_abu-dawud_811"],"ونصحت ثم":["h_abu-dawud_1565"],"ونصوم حتى":["h_abu-dawud_1989"],"ونصلحها":["h_abu-dawud_2086"],"ونصلحها فأنزل":["h_abu-dawud_2086"],"ونصلحها وندع":["h_abu-dawud_2086"],"ونصيري":["h_abu-dawud_2197"],"ونصيري بك":["h_abu-dawud_2197"],"ونصفا":["h_abu-dawud_2546","h_abu-dawud_2777"],"ونصفا بين":["h_abu-dawud_2546"],"ونصفا بمد":["h_abu-dawud_2777"],"ونصطبحقال":["h_abu-dawud_3242"],"ونصطبحقال أبو":["h_abu-dawud_3242"],"ونصيرا":["q_25_31"],"ونصروا":["q_8_72","q_8_74","h_bukhari_1485"],"ونصروا اولۤىك":["q_8_72","q_8_74"],"ونصف الدية":["h_ahmad_39"],"ونصبه":["h_ahmad_1154"],"ونصبه قدمه":["h_ahmad_1154"],"ونصبه أصبعه":["h_ahmad_1154"],"ونصبت":["h_ahmad_1154"],"ونصبت السبابة":["h_ahmad_1154"],"ونصرنهم":["q_37_116"],"ونصرنهم فكانوا":["q_37_116"],"ونصحت لكم":["q_7_79"],"ونصحت لكمۚ":["q_7_93"],"ونصروه":["q_7_157","h_bukhari_3341"],"ونصروه واتبعوا":["q_7_157"],"ونصيحته إلى":["h_bukhari_407","h_bukhari_4677"],"ونصب بين":["h_bukhari_471"],"ونصب الأخرى":["h_bukhari_785"],"ونصروا أولئك":["h_bukhari_1485"],"ونصف فقدم":["h_bukhari_2897"],"ونصف قال":["h_bukhari_2897"],"ونصروه أو":["h_bukhari_3341"],"ونصف من":["h_bukhari_3666"],"ونصر الضعيف":["h_bukhari_5461"],"ونصبني":["h_bukhari_6056"],"ونصبني للناس":["h_bukhari_6056"],"ونصيب منك":["h_darimi_412"],"ونصيحة":["h_darimi_414"],"ونصيحة منكم":["h_darimi_414"],"ونصب إصبعه":["h_darimi_952"],"ونصف في":["h_darimi_1224"],"ونصف حظ":["h_darimi_2478"],"ونصف فريضة":["h_darimi_2649"],"ونضح":["h_malik_90","h_malik_100","h_nasai_135","h_tirmidzi_305","h_abu-dawud_134","h_ahmad_314","h_ahmad_1644","h_ahmad_1794","h_ahmad_1795","h_ahmad_3413","h_ahmad_3441","h_bukhari_630","h_bukhari_1108","h_darimi_472"],"ونضح في":["h_malik_90"],"ونضح ما":["h_malik_100"],"ونضيجة":["h_muslim_3347","h_ibnu-majah_3150"],"ونضيجة ثم":["h_muslim_3347","h_ibnu-majah_3150"],"ونضح فرجه":["h_nasai_135","h_abu-dawud_134","h_ahmad_1644","h_ahmad_1795","h_ahmad_3413","h_ahmad_3441","h_darimi_472"],"ونضع":["q_21_47","h_tirmidzi_2931"],"ونضع الموازين":["q_21_47","h_tirmidzi_2931"],"ونضح بساط":["h_tirmidzi_305"],"ونضح فرجهحدثنا":["h_ahmad_314"],"ونضحنا":["h_ahmad_1593"],"ونضحنا عليه":["h_ahmad_1593"],"ونضححدثنا":["h_ahmad_1644"],"ونضححدثنا الأسود":["h_ahmad_1644"],"ونضح على":["h_ahmad_1794"],"ونضح طرف":["h_bukhari_630"],"ونضح له":["h_bukhari_1108"],"ونضربهما":["h_bukhari_3885"],"ونضربهما فقال":["h_bukhari_3885"],"ونضرة":["h_ibnu-majah_4279"],"ونضرة في":["h_ibnu-majah_4279"],"ونطعم":["h_nasai_3948","h_tirmidzi_3513","h_darimi_41","h_darimi_412"],"ونطعم من":["h_nasai_3948"],"ونطعم وكان":["h_tirmidzi_3513"],"ونطهرها":["h_abu-dawud_373"],"ونطبع":["q_7_100"],"ونطبع على":["q_7_100"],"ونطوي":["h_bukhari_4205"],"ونطوي بطوننا":["h_bukhari_4205"],"ونطعم قال":["h_darimi_41"],"ونطعم الطعام":["h_darimi_412"],"ونطمع":["q_5_84"],"ونطمع ان":["q_5_84"],"ونطرد":["h_ibnu-majah_959"],"ونطرد عنها":["h_ibnu-majah_959"],"ونظرنا":["h_malik_201","h_nasai_1202","h_ahmad_3363","h_bukhari_1148"],"ونظرنا تسليمه":["h_malik_201","h_nasai_1202","h_ahmad_3363","h_bukhari_1148"],"ونظرت":["h_muslim_3095","h_abu-dawud_1734","h_ahmad_3906","h_bukhari_1879","h_bukhari_4236"],"ونظرت إلى":["h_muslim_3095","h_abu-dawud_1734"],"ونظر":["h_muslim_4286","h_tirmidzi_1955","h_tirmidzi_2416","h_abu-dawud_3623"],"ونظر إليها":["h_muslim_4286","h_tirmidzi_2416"],"ونظر ابن":["h_tirmidzi_1955"],"ونظر إلى":["h_abu-dawud_3623"],"ونظرت له":["h_ahmad_3906"],"ونظفتهم":["h_ahmad_3927"],"ونظفتهم فقال":["h_ahmad_3927"],"ونظرت إليه":["h_bukhari_1879"],"ونظره":["h_bukhari_3779"],"ونظره في":["h_bukhari_3779"],"ونظرت عن":["h_bukhari_4236"],"ونظرت أمامي":["h_bukhari_4236"],"ونظرت خلفي":["h_bukhari_4236"],"ونعلم":["q_50_16","h_darimi_345","q_5_113"],"ونعلم ما":["q_50_16"],"ونعمنا":["h_malik_1458"],"ونعمنا الله":["h_malik_1458"],"ونعم":["h_malik_1586","q_3_136","q_3_173","h_muslim_1658","h_muslim_4149","h_muslim_4286","h_nasai_443","h_nasai_2449","h_tirmidzi_2347","h_tirmidzi_2995","q_22_78","h_abu-dawud_1140","h_abu-dawud_1252","h_abu-dawud_3065","q_8_40","h_ahmad_1317","h_ahmad_1779","h_ahmad_1780","h_ahmad_3742","h_bukhari_2630","h_bukhari_2831","h_bukhari_3414","h_bukhari_3892","h_bukhari_3893","h_ibnu-majah_1577"],"ونعم ابن":["h_malik_1586","h_bukhari_2831"],"ونعم اجر":["q_3_136"],"ونعم الوكيل":["q_3_173","h_muslim_4286","h_tirmidzi_2347","h_tirmidzi_2995","h_abu-dawud_1252","h_abu-dawud_3065","h_bukhari_3892","h_bukhari_3893"],"ونعيمۙ":["q_52_17"],"ونعله":["h_muslim_130","h_nasai_111","h_abu-dawud_3497"],"ونعله حسنة":["h_muslim_130"],"ونعم صاحب":["h_muslim_1658","h_nasai_2449","h_bukhari_2630"],"ونعمهم":["h_muslim_1670","h_abu-dawud_2075"],"ونعمهم ومع":["h_muslim_1670"],"ونعزل":["h_muslim_2423"],"ونعزل فقلنا":["h_muslim_2423"],"ونعم السلف":["h_muslim_4149","h_ahmad_3742","h_ibnu-majah_1577"],"ونعله وترجلهقال":["h_nasai_111"],"ونعم المجيء":["h_nasai_443","h_ahmad_1779","h_ahmad_1780"],"ونعمت":["h_nasai_1354","h_tirmidzi_457","h_abu-dawud_288","h_ahmad_2574","h_darimi_1143","h_ibnu-majah_1048"],"ونعمت ومن":["h_nasai_1354","h_tirmidzi_457","h_abu-dawud_288","h_ahmad_2574","h_darimi_1143"],"ونعوذ":["h_nasai_1378","h_nasai_3133","h_tirmidzi_1023","h_tirmidzi_2178","h_tirmidzi_3248","h_abu-dawud_912","h_abu-dawud_1271","h_abu-dawud_1744","h_ahmad_2787","h_ahmad_2927","h_ahmad_3458","h_darimi_1750","h_ibnu-majah_1847","h_ibnu-majah_1848"],"ونعوذ بالله":["h_nasai_1378","h_nasai_3133","h_tirmidzi_1023","h_abu-dawud_912","h_ahmad_3458","h_darimi_1750","h_ibnu-majah_1847","h_ibnu-majah_1848"],"ونعيم":["h_nasai_4554","h_tirmidzi_435","h_tirmidzi_3249","h_abu-dawud_924","h_bukhari_740","h_darimi_1215","h_darimi_1219","h_darimi_1226","h_darimi_1904"],"ونعيم بن":["h_nasai_4554","h_tirmidzi_435","h_tirmidzi_3249","h_abu-dawud_924","h_darimi_1215","h_darimi_1219","h_darimi_1226","h_darimi_1904"],"ونعلي":["h_tirmidzi_1922","h_abu-dawud_2583"],"ونعلي حسنة":["h_tirmidzi_1922"],"ونعوذ بك":["h_tirmidzi_2178","h_tirmidzi_3248","h_abu-dawud_1271","h_ahmad_2927"],"ونعيمه":["h_tirmidzi_2409"],"ونعيمه وخدمه":["h_tirmidzi_2409"],"ونعادي":["h_tirmidzi_3170"],"ونعادي بعداوتك":["h_tirmidzi_3170"],"ونعليه":["h_tirmidzi_3486"],"ونعليه وحذيفة":["h_tirmidzi_3486"],"ونعم النصير":["q_22_78","q_8_40"],"ونعمة":["q_44_27","h_ahmad_2089","q_49_8","h_darimi_2509"],"ونعمة كانوا":["q_44_27"],"ونعمهۙ":["q_89_15"],"ونعمهۙ فيقول":["q_89_15"],"ونعمل":["h_abu-dawud_658"],"ونعمل بأيدينا":["h_abu-dawud_658"],"ونعم ما":["h_abu-dawud_1140"],"ونعتت":["h_abu-dawud_1225"],"ونعتت قراءته":["h_abu-dawud_1225"],"ونعيمها":["h_abu-dawud_1235"],"ونعيمها وبهجتها":["h_abu-dawud_1235"],"ونعوذ به":["h_abu-dawud_1744","h_ahmad_2787"],"ونعمهم وشائهم":["h_abu-dawud_2075"],"ونعين":["h_abu-dawud_2288","h_ahmad_3202","h_ahmad_3973"],"ونعين به":["h_abu-dawud_2288","h_ahmad_3202"],"ونعلي ومجني":["h_abu-dawud_2583"],"ونعله قال":["h_abu-dawud_3497"],"ونعبده":["h_ahmad_134","h_ahmad_3270"],"ونعبده ونخلع":["h_ahmad_134","h_ahmad_3270"],"ونعالنا":["h_ahmad_582","h_bukhari_5948","h_ibnu-majah_3178"],"ونعالنا وأرديتنا":["h_ahmad_582","h_bukhari_5948"],"ونعاه":["h_ahmad_1249"],"ونعاه رسول":["h_ahmad_1249"],"ونعم فتى":["h_ahmad_1317"],"ونعت":["h_ahmad_2016"],"ونعت لي":["h_ahmad_2016"],"ونعمة والله":["h_ahmad_2089"],"ونعين المسلمين":["h_ahmad_3973"],"ونعيم المجمر":["h_bukhari_740"],"ونعبد":["h_bukhari_2925"],"ونعبد الشجر":["h_bukhari_2925"],"ونعم الجن":["h_bukhari_3414"],"ونعود":["h_bukhari_4913"],"ونعود المريض":["h_bukhari_4913"],"ونعمة ۗوالله":["q_49_8"],"ونعلم الناس":["h_darimi_345"],"ونعلين":["h_darimi_357"],"ونعلين من":["h_darimi_357"],"ونعمة أحق":["h_darimi_2509"],"ونعلم ان":["q_5_113"],"ونعتزلهم":["h_ibnu-majah_219"],"ونعتزلهم بديننا":["h_ibnu-majah_219"],"ونعما":["h_ibnu-majah_243"],"ونعما إن":["h_ibnu-majah_243"],"ونعمت تجزئ":["h_ibnu-majah_1048"],"ونعالنا فقال":["h_ibnu-majah_3178"],"ونغزل":["h_ahmad_3202","h_ahmad_3932"],"ونغزل الشعر":["h_ahmad_3202","h_ahmad_3932"],"ونغسلها":["h_bukhari_2297","h_bukhari_3632","h_bukhari_4768","h_bukhari_5377","h_bukhari_5551","h_ibnu-majah_3151"],"ونغسلها قال":["h_bukhari_2297","h_bukhari_3632","h_bukhari_5377","h_bukhari_5551"],"ونغسلها فقال":["h_bukhari_4768","h_ibnu-majah_3151"],"ونغرف":["h_darimi_41"],"ونغرف لهم":["h_darimi_41"],"ونغتسل":["h_ibnu-majah_317"],"ونغتسل من":["h_ibnu-majah_317"],"ونغطي":["h_ibnu-majah_322"],"ونغطي آنيتنا":["h_ibnu-majah_322"],"ونفخ":["q_18_99","q_50_20","h_malik_839","h_muslim_281","h_muslim_4451","h_nasai_314","h_nasai_315","h_nasai_2854","q_32_9","h_tirmidzi_2060","h_tirmidzi_2350","h_tirmidzi_2997","h_tirmidzi_3119","h_abu-dawud_264","q_36_51","h_ahmad_2213","h_bukhari_326","h_bukhari_3046","h_bukhari_4038","q_39_68","h_ibnu-majah_4224"],"ونفخ فى":["q_18_99","q_50_20","q_36_51","q_39_68"],"ونفس":["h_malik_23","h_malik_24","h_muslim_946","h_muslim_947","h_muslim_948","h_nasai_5082","h_nasai_5110","h_ahmad_43","q_91_7","h_bukhari_504","h_bukhari_2991","h_bukhari_5831","h_darimi_2367","h_ibnu-majah_4267"],"ونفس في":["h_malik_23","h_malik_24","h_muslim_946","h_muslim_947","h_muslim_948","h_bukhari_504","h_bukhari_2991","h_darimi_2367","h_ibnu-majah_4267"],"ونفسه":["h_malik_138","h_muslim_29","h_muslim_30","h_muslim_573","h_muslim_863","h_muslim_1449","h_muslim_3261","h_muslim_4780","h_muslim_4834","h_nasai_663","h_nasai_1800","h_nasai_2315","h_nasai_2394","h_nasai_2948","h_nasai_2950","h_nasai_3731","h_nasai_3733","h_tirmidzi_2465","h_abu-dawud_421","h_abu-dawud_1208","h_abu-dawud_1283","h_abu-dawud_2642","h_abu-dawud_3931","h_ahmad_328","h_ahmad_1581","h_bukhari_573","h_bukhari_1155","h_bukhari_1204","h_bukhari_1312","h_bukhari_4918","h_bukhari_6079","h_bukhari_6403","h_bukhari_6476","h_bukhari_6539","h_darimi_825","h_darimi_1035","h_darimi_1103","h_ibnu-majah_4027"],"ونفسه يقول":["h_malik_138","h_muslim_573","h_muslim_863","h_nasai_663","h_bukhari_573","h_bukhari_1155"],"ونفعه":["h_malik_495","h_muslim_3913","h_bukhari_77"],"ونفعه الله":["h_malik_495"],"ونفطر":["h_malik_576"],"ونفطر نحن":["h_malik_576"],"ونفروا":["h_malik_811"],"ونفخ بيده":["h_malik_839","h_nasai_2854"],"ونفلوا":["h_malik_856","h_muslim_3057","h_muslim_3058","h_abu-dawud_2299","h_bukhari_2901","h_darimi_2015"],"ونفلوا بعيرا":["h_malik_856","h_muslim_3057","h_abu-dawud_2299","h_bukhari_2901","h_darimi_2015"],"ونفر":["h_malik_1274","h_nasai_2417","h_nasai_5296","h_ahmad_743","h_ahmad_3012","h_bukhari_2841","h_bukhari_3589"],"ونفر من":["h_malik_1274","h_nasai_2417","h_nasai_5296","h_ahmad_743"],"ونفاه":["h_malik_1295","h_ibnu-majah_2619"],"ونفاه ولم":["h_malik_1295"],"ونفسه إلا":["h_muslim_29","h_muslim_30","h_nasai_2315","h_nasai_2948","h_nasai_2950","h_nasai_3731","h_nasai_3733","h_tirmidzi_2465","h_abu-dawud_1283","h_bukhari_1312","h_bukhari_6079","h_bukhari_6403"],"ونفخ فيك":["h_muslim_281","h_muslim_4451","h_tirmidzi_2060","h_tirmidzi_2350","h_bukhari_3046","h_bukhari_4038"],"ونفسه تقعقع":["h_muslim_1449","h_nasai_1800","h_abu-dawud_2642","h_bukhari_6476"],"ونفهت":["h_muslim_1861","h_nasai_2274","h_bukhari_1085","h_bukhari_1843","h_bukhari_3109"],"ونفهت النفس":["h_muslim_1861","h_bukhari_3109"],"ونفي":["h_muslim_2966","h_tirmidzi_1354","h_abu-dawud_3718","h_ahmad_721","h_ahmad_3306","h_ahmad_3319","h_darimi_1869"],"ونفي سنة":["h_muslim_2966","h_ahmad_721","h_ahmad_3306","h_ahmad_3319","h_darimi_1869"],"ونفلوا سوى":["h_muslim_3058"],"ونفلنا":["h_muslim_3059","h_abu-dawud_2300","h_bukhari_3715"],"ونفلنا رسول":["h_muslim_3059","h_abu-dawud_2300"],"ونفسه قال":["h_muslim_3261"],"ونفض":["h_muslim_3864"],"ونفض شعبة":["h_muslim_3864"],"ونفعه بما":["h_muslim_3913"],"ونفث":["h_muslim_4624","h_nasai_1830","h_nasai_1947","h_ahmad_381","h_ahmad_1305","h_ahmad_2369","h_bukhari_1263","h_bukhari_5044"],"ونفث عليه":["h_muslim_4624","h_nasai_1830","h_nasai_1947","h_bukhari_1263","h_bukhari_5044"],"ونفسه وولده":["h_muslim_4780"],"ونفسه ينتهي":["h_muslim_4834","h_ibnu-majah_4027"],"ونفخ في":["h_nasai_314","h_tirmidzi_2997","h_ahmad_2213","h_ibnu-majah_4224"],"ونفخ فيها":["h_nasai_315"],"ونفهت له":["h_nasai_2274","h_bukhari_1843"],"ونفسه قيل":["h_nasai_2394","h_abu-dawud_1208","h_ahmad_328","h_darimi_1035"],"ونفست":["h_nasai_4361"],"ونفست فيها":["h_nasai_4361"],"ونفس لا":["h_nasai_5082","h_nasai_5110"],"ونفخ فيه":["q_32_9","h_tirmidzi_3119"],"ونفخه":["h_tirmidzi_225","h_abu-dawud_638","h_abu-dawud_645","h_ahmad_1284","h_ahmad_1285","h_darimi_858","h_ibnu-majah_767","h_ibnu-majah_768"],"ونفخه ونفثهقال":["h_tirmidzi_225","h_ibnu-majah_767"],"ونفثهقال":["h_tirmidzi_225","h_ibnu-majah_767"],"ونفثهقال أبو":["h_tirmidzi_225"],"ونفي سنةقال":["h_tirmidzi_1354"],"ونفسا":["h_tirmidzi_2450"],"ونفسا في":["h_tirmidzi_2450"],"ونفاق":["h_tirmidzi_2489"],"ونفاق التكذيب":["h_tirmidzi_2489"],"ونفضل":["h_tirmidzi_2894","q_13_4"],"ونفضل بعضها":["h_tirmidzi_2894","q_13_4"],"ونفور":["q_67_21"],"ونفاقا":["q_9_97"],"ونفاقا واجدر":["q_9_97"],"ونفسه ويقول":["h_abu-dawud_421"],"ونفثه":["h_abu-dawud_638","h_abu-dawud_645","h_ahmad_1284","h_ahmad_1285","h_darimi_858","h_ibnu-majah_767","h_ibnu-majah_768"],"ونفثه وهمزهقال":["h_abu-dawud_638"],"ونفخه الكبر":["h_abu-dawud_638","h_darimi_858","h_ibnu-majah_767","h_ibnu-majah_768"],"ونفخه ونفثه":["h_abu-dawud_645","h_ibnu-majah_768"],"ونفثه ثم":["h_abu-dawud_645"],"ونفى":["h_abu-dawud_1548","h_ibnu-majah_2908"],"ونفى الكفر":["h_abu-dawud_1548","h_ibnu-majah_2908"],"ونفرا":["h_abu-dawud_1879","h_ahmad_2774"],"ونفرا من":["h_abu-dawud_1879","h_ahmad_2774"],"ونفل":["h_abu-dawud_2297","h_ahmad_1524"],"ونفل أهل":["h_abu-dawud_2297"],"ونفلنا بعيرا":["h_abu-dawud_2300","h_bukhari_3715"],"ونفقة":["h_abu-dawud_2508"],"ونفقة أهله":["h_abu-dawud_2508"],"ونفعل":["h_abu-dawud_3593"],"ونفعل قال":["h_abu-dawud_3593"],"ونفي سنةحدثنا":["h_abu-dawud_3718"],"ونفسه من":["h_abu-dawud_3931"],"ونفسك":["h_abu-dawud_3931","h_darimi_52"],"ونفسك من":["h_abu-dawud_3931"],"ونفس الله":["h_ahmad_43"],"ونفث فلما":["h_ahmad_381"],"ونفثه ونفخه":["h_ahmad_1284","h_ahmad_1285","h_darimi_858"],"ونفخه قلت":["h_ahmad_1284"],"ونفخه قال":["h_ahmad_1284","h_ahmad_1285"],"ونفثه الشعر":["h_ahmad_1284","h_darimi_858","h_ibnu-majah_767","h_ibnu-majah_768"],"ونفث فيه":["h_ahmad_1305","h_ahmad_2369"],"ونفل الثلث":["h_ahmad_1524"],"ونفسه حرمة":["h_ahmad_1581"],"ونفر معه":["h_ahmad_3012"],"ونفخت":["q_15_29","q_38_72"],"ونفخت فيه":["q_15_29","q_38_72"],"ونفس وما":["q_91_7"],"ونفعه ما":["h_bukhari_77"],"ونفخ فيهما":["h_bukhari_326"],"ونفرنا":["h_bukhari_331"],"ونفرنا خلوفا":["h_bukhari_331"],"ونفهت نفسك":["h_bukhari_1085"],"ونفسه تتقعقع":["h_bukhari_1204"],"ونفر فصاح":["h_bukhari_2841"],"ونفر معك":["h_bukhari_3589"],"ونفضته":["h_bukhari_3797"],"ونفضته وطيبته":["h_bukhari_3797"],"ونفشي":["h_bukhari_4913"],"ونفشي السلام":["h_bukhari_4913"],"ونفسه جئث":["h_bukhari_4918"],"ونفس الصبي":["h_bukhari_5831"],"ونفسه تقلقل":["h_bukhari_6539"],"ونفسك مطمئنة":["h_darimi_52"],"ونفسه فيقول":["h_darimi_825","h_darimi_1103"],"ونفخه ثم":["h_darimi_858"],"ونفثهقال عمرو":["h_ibnu-majah_767"],"ونفثه قال":["h_ibnu-majah_768"],"ونفيتك":["h_ibnu-majah_2568"],"ونفيتك من":["h_ibnu-majah_2568"],"ونفاه سنة":["h_ibnu-majah_2619"],"ونقول":["q_3_181","h_ahmad_4208"],"ونقول ذوقوا":["q_3_181"],"ونقدس":["q_2_30"],"ونقدس لك":["q_2_30"],"ونقص":["q_2_155","h_muslim_235","h_muslim_266","h_muslim_1061","h_muslim_1716","h_muslim_4310","h_nasai_2061","h_nasai_2068","q_7_130"],"ونقص من":["q_2_155","q_7_130"],"ونقصان":["h_muslim_9","h_tirmidzi_2471"],"ونقصان أحرف":["h_muslim_9"],"ونقص شيئا":["h_muslim_266"],"ونقوم":["h_muslim_1021","h_ahmad_540","h_ahmad_2859","h_bukhari_313","h_bukhari_1542","h_bukhari_5430"],"ونقوم خلفه":["h_muslim_1021","h_bukhari_5430"],"ونقص وقال":["h_muslim_1061"],"ونقه":["h_muslim_1514","h_muslim_1515","h_nasai_62","h_nasai_1912","h_nasai_1913","h_ahmad_3716","h_ibnu-majah_1456"],"ونقه من":["h_muslim_1514","h_muslim_1515","h_nasai_62","h_nasai_1912","h_nasai_1913","h_ahmad_3716","h_ibnu-majah_1456"],"ونقص في":["h_muslim_1716","h_nasai_2061","h_nasai_2068"],"ونقتل":["h_muslim_3196"],"ونقتل أنفسنا":["h_muslim_3196"],"ونقتطع":["h_muslim_3336"],"ونقتطع منه":["h_muslim_3336"],"ونقير":["h_muslim_3461"],"ونقير ودباء":["h_muslim_3461"],"ونقش":["h_muslim_3607","h_muslim_3608","h_muslim_3611","h_nasai_4840","h_nasai_4845","h_nasai_4852","h_nasai_4860","h_nasai_4861","h_nasai_4922","h_nasai_4932","h_abu-dawud_3567","h_abu-dawud_3570","h_bukhari_2721","h_bukhari_5112","h_bukhari_5123"],"ونقش فيه":["h_muslim_3607","h_muslim_3608","h_muslim_3611","h_nasai_4840","h_nasai_4845","h_nasai_4860","h_nasai_4861","h_nasai_4922","h_abu-dawud_3567","h_abu-dawud_3570","h_bukhari_2721","h_bukhari_5112","h_bukhari_5123"],"ونقشت":["h_muslim_3608","h_bukhari_5123"],"ونقشت فيه":["h_muslim_3608","h_bukhari_5123"],"ونقر":["h_muslim_4019","q_22_5","h_bukhari_3300"],"ونقر عنه":["h_muslim_4019"],"ونقص ومما":["h_muslim_4310"],"ونق":["h_muslim_4532","h_nasai_61","h_nasai_330","h_nasai_5117","h_bukhari_5586","h_bukhari_5593","h_bukhari_5595","h_ibnu-majah_3792"],"ونق قلبي":["h_muslim_4532","h_nasai_61","h_nasai_330","h_nasai_5117","h_bukhari_5586","h_bukhari_5593","h_bukhari_5595","h_ibnu-majah_3792"],"ونقش عليه":["h_nasai_4852","h_nasai_4932"],"ونقشنا":["h_nasai_4852","h_nasai_4925","h_nasai_4926","h_bukhari_5120","h_ibnu-majah_3595"],"ونقشنا فيه":["h_nasai_4852","h_bukhari_5120","h_ibnu-majah_3595"],"ونقشه":["h_nasai_4921","h_ahmad_2252","h_bukhari_5121","h_bukhari_6295","h_ibnu-majah_3596"],"ونقشه محمد":["h_nasai_4921","h_bukhari_5121","h_bukhari_6295","h_ibnu-majah_3596"],"ونقشنا عليه":["h_nasai_4925","h_nasai_4926"],"ونقصان دينكن":["h_tirmidzi_2471"],"ونقر فى":["q_22_5"],"ونقطع":["h_ahmad_134","h_ahmad_3270"],"ونقطع الأرحام":["h_ahmad_134","h_ahmad_3270"],"ونقوم بالحق":["h_ahmad_540"],"ونقرئه":["h_ahmad_1532","h_ahmad_1839","h_ibnu-majah_4000"],"ونقرئه أبناءنا":["h_ahmad_1532","h_ahmad_1839","h_ibnu-majah_4000"],"ونقسم":["h_ahmad_1593"],"ونقسم لحمه":["h_ahmad_1593"],"ونقشه الله":["h_ahmad_2252"],"ونقوم على":["h_ahmad_2859","h_bukhari_313","h_bukhari_1542"],"ونقول كما":["h_ahmad_4208"],"ونقيل":["h_bukhari_854"],"ونقيل بعد":["h_bukhari_854"],"ونقدني":["h_bukhari_2517"],"ونقدني ثمنه":["h_bukhari_2517"],"ونقر بيديه":["h_bukhari_3300"],"ونقبت":["h_bukhari_3602"],"ونقبت قدماي":["h_bukhari_3602"],"ونقوا":["h_bukhari_5749"],"ونقوا أذن":["h_bukhari_5749"],"ونقلب":["q_6_110"],"ونقلب افـدتهم":["q_6_110"],"ونقرة":["h_darimi_936"],"ونقرة الغراب":["h_darimi_936"],"ونكفر":["q_4_150"],"ونكفر ببعضۙ":["q_4_150"],"ونكص":["h_muslim_624","h_bukhari_712"],"ونكص أبو":["h_muslim_624","h_bukhari_712"],"ونكصت":["h_muslim_2394","h_abu-dawud_1856","h_bukhari_4073","h_ibnu-majah_2022"],"ونكصت على":["h_muslim_2394"],"ونكره":["h_muslim_3126"],"ونكره أن":["h_muslim_3126"],"ونكس":["h_muslim_3975","h_darimi_845"],"ونكس أصحابه":["h_muslim_3975"],"ونكحها":["h_muslim_4142","h_bukhari_4485"],"ونكحها فنكحت":["h_muslim_4142","h_bukhari_4485"],"ونكبر":["h_nasai_1146","h_nasai_1325","h_bukhari_798","h_darimi_967"],"ونكبر ونحمد":["h_nasai_1146"],"ونكبر أربعا":["h_nasai_1325","h_bukhari_798","h_darimi_967"],"ونكاح":["h_tirmidzi_1028","h_tirmidzi_1061","h_tirmidzi_1063","h_abu-dawud_1869","h_bukhari_4427"],"ونكاح الآخر":["h_tirmidzi_1028"],"ونكاح جديدقال":["h_tirmidzi_1061"],"ونكاح جديد":["h_tirmidzi_1063"],"ونكحت":["h_tirmidzi_2360","h_bukhari_86","h_bukhari_2446"],"ونكحت فاطمة":["h_tirmidzi_2360"],"ونكست":["h_tirmidzi_2945"],"ونكست حتى":["h_tirmidzi_2945"],"ونكتب":["h_tirmidzi_2979","q_36_12","h_bukhari_616","h_ibnu-majah_745"],"ونكتب ما":["h_tirmidzi_2979","q_36_12","h_bukhari_616","h_ibnu-majah_745"],"ونكبره":["h_tirmidzi_3164"],"ونكبره أربعا":["h_tirmidzi_3164"],"ونكح":["h_abu-dawud_1812","h_ahmad_3276","h_bukhari_3450"],"ونكح امرأة":["h_abu-dawud_1812"],"ونكصت حتى":["h_abu-dawud_1856","h_bukhari_4073","h_ibnu-majah_2022"],"ونكاح آخر":["h_abu-dawud_1869","h_bukhari_4427"],"ونكاح رابع":["h_abu-dawud_1869"],"ونكون":["h_ahmad_2787","q_6_27","q_28_47","q_5_113"],"ونكون في":["h_ahmad_2787"],"ونكح النساء":["h_ahmad_3276"],"ونكحت زوجا":["h_bukhari_86","h_bukhari_2446"],"ونكح عائشة":["h_bukhari_3450"],"ونكاح الرابع":["h_bukhari_4427"],"ونكون من":["q_6_27","q_28_47"],"ونكس ساعة":["h_darimi_845"],"ونكاحه":["h_darimi_2701"],"ونكاحه ولا":["h_darimi_2701"],"ونكون عليها":["q_5_113"],"ونلعبۗ":["q_9_65"],"ونلعبۗ قل":["q_9_65"],"ونلطخه":["h_abu-dawud_2395"],"ونلطخه بزعفران":["h_abu-dawud_2395"],"ونلت":["h_ahmad_1568","h_bukhari_3464"],"ونلت صهره":["h_ahmad_1568"],"ونلبس":["h_bukhari_2925"],"ونلبس الوبر":["h_bukhari_2925"],"ونلت صهر":["h_bukhari_3464"],"ونمنعكم":["q_4_141"],"ونمنعكم من":["q_4_141"],"ونميت":["q_50_43","q_15_23"],"ونميت والينا":["q_50_43"],"ونمد":["q_19_79","h_bukhari_4061"],"ونمد له":["q_19_79","h_bukhari_4061"],"ونم":["h_muslim_1856","h_muslim_1860","h_nasai_2266","h_nasai_2268","h_nasai_2276","h_abu-dawud_1133","h_abu-dawud_2007","h_bukhari_1085","h_bukhari_1839","h_bukhari_1840","h_bukhari_1841","h_bukhari_3108","h_bukhari_4495","h_bukhari_5364"],"ونم وقم":["h_muslim_1856","h_nasai_2268"],"ونم وصم":["h_muslim_1860","h_nasai_2266","h_nasai_2276","h_abu-dawud_2007","h_bukhari_1840","h_bukhari_3108","h_bukhari_5364"],"ونمى":["h_muslim_4375","h_ahmad_4086","h_ahmad_4092"],"ونمى خيرا":["h_muslim_4375","h_ahmad_4086"],"ونمير":["h_tirmidzi_271","q_12_65","h_ahmad_2781"],"ونمير الخزاعي":["h_tirmidzi_271"],"ونمي":["h_tirmidzi_1588"],"ونمي له":["h_tirmidzi_1588"],"ونمت":["h_tirmidzi_3065"],"ونمت كئيبا":["h_tirmidzi_3065"],"ونمارق":["q_88_15"],"ونمارق مصفوفة":["q_88_15"],"ونمير اهلنا":["q_12_65"],"ونمير بن":["h_ahmad_2781"],"ونمى خير":["h_ahmad_4092"],"ونميت ونحن":["q_15_23"],"ونمسح":["h_bukhari_158"],"ونمسح على":["h_bukhari_158"],"ونم فإن":["h_bukhari_1839","h_bukhari_1841","h_bukhari_4495"],"ونمنا":["h_bukhari_2694"],"ونمنا نومة":["h_bukhari_2694"],"ونمكن":["q_28_6"],"ونمكن لهم":["q_28_6"],"وننقل":["h_muslim_3133","h_bukhari_3359"],"وننقل التراب":["h_muslim_3133","h_bukhari_3359"],"وننبذه":["h_muslim_3463","h_tirmidzi_1794","h_ibnu-majah_3354"],"وننبذه عشاء":["h_muslim_3463","h_tirmidzi_1794"],"وننشئكم":["q_56_61"],"وننشئكم في":["q_56_61"],"ونناول":["h_abu-dawud_2288"],"ونناول السهام":["h_abu-dawud_2288"],"وننظر":["h_ahmad_1830"],"وننظر ما":["h_ahmad_1830"],"وننال":["h_bukhari_6"],"وننال منه":["h_bukhari_6"],"وننفخه":["h_bukhari_4688"],"وننفخه فيطير":["h_bukhari_4688"],"وننهى":["h_darimi_345"],"وننهى عن":["h_darimi_345"],"وننزل":["h_darimi_2804","q_17_82"],"وننزل من":["h_darimi_2804","q_17_82"],"وننبذه عشية":["h_ibnu-majah_3354"],"ونهى":["h_malik_453","h_malik_852","h_malik_982","h_malik_1153","h_malik_1172","h_malik_1325","h_muslim_379","h_muslim_1818","h_muslim_3006","h_muslim_3426","h_muslim_4620","h_nasai_40","h_nasai_555","h_nasai_716","h_nasai_2691","h_nasai_3683","h_nasai_4515","h_nasai_4516","h_nasai_4770","h_nasai_5196","h_nasai_5200","h_nasai_5202","h_nasai_5280","h_nasai_5283","h_tirmidzi_1472","h_tirmidzi_1482","h_tirmidzi_1494","h_tirmidzi_1671","h_tirmidzi_1718","h_tirmidzi_1791","h_tirmidzi_1798","h_tirmidzi_2645","q_79_40","h_abu-dawud_174","h_abu-dawud_898","h_abu-dawud_1725","h_abu-dawud_1824","h_abu-dawud_2327","h_abu-dawud_2894","h_abu-dawud_3137","h_abu-dawud_3840","h_abu-dawud_4036","h_ahmad_288","h_ahmad_640","h_ahmad_653","h_ahmad_2865","h_bukhari_1857","h_bukhari_1944","h_bukhari_2000","h_bukhari_2005","h_bukhari_2019","h_bukhari_2053","h_bukhari_2091","h_bukhari_2525","h_bukhari_3779","h_bukhari_4004","h_bukhari_4623","h_bukhari_4994","h_bukhari_5183","h_bukhari_5461","h_bukhari_5480","h_bukhari_6350","h_ibnu-majah_277","h_ibnu-majah_3351"],"ونهى رسول":["h_malik_453","h_muslim_1818","h_muslim_4620","h_nasai_555","h_nasai_5283","h_abu-dawud_2327","h_ahmad_288","h_bukhari_3779","h_bukhari_5480","h_bukhari_6350"],"ونهى عن":["h_malik_852","h_malik_982","h_muslim_379","h_muslim_3006","h_nasai_40","h_nasai_2691","h_nasai_3683","h_nasai_4770","h_nasai_5200","h_nasai_5280","h_tirmidzi_1482","h_tirmidzi_1494","h_tirmidzi_1718","h_tirmidzi_1791","h_tirmidzi_1798","h_tirmidzi_2645","h_abu-dawud_174","h_abu-dawud_898","h_abu-dawud_1725","h_abu-dawud_2894","h_ahmad_2865","h_bukhari_1944","h_bukhari_2000","h_bukhari_2053","h_bukhari_2091","h_bukhari_2525","h_bukhari_4623","h_bukhari_4994","h_bukhari_5183","h_bukhari_5461","h_ibnu-majah_277"],"ونهيتكم":["h_malik_914","h_muslim_1537","h_muslim_3402","h_nasai_1960","h_nasai_1961","h_nasai_4137","h_nasai_5287","h_nasai_5288","h_abu-dawud_3134"],"ونهيتكم عن":["h_malik_914","h_muslim_1537","h_muslim_3402","h_nasai_1960","h_nasai_1961","h_nasai_4137","h_nasai_5287","h_nasai_5288","h_abu-dawud_3134"],"ونهاه":["h_malik_926","h_ahmad_2744","h_darimi_1800"],"ونهاه عن":["h_malik_926"],"ونهى عنهو":["h_malik_1153"],"ونهى عنه":["h_malik_1172","h_abu-dawud_1824"],"ونهى عنهاقال":["h_malik_1325"],"ونهاهم":["h_muslim_24","h_abu-dawud_517","h_abu-dawud_2504","h_bukhari_51","h_bukhari_85","h_bukhari_6386","h_darimi_930"],"ونهاهم عن":["h_muslim_24","h_bukhari_51","h_bukhari_85","h_bukhari_6386"],"ونهران":["h_muslim_237","h_nasai_443","h_ahmad_1779","h_ahmad_1780","h_bukhari_2968","h_bukhari_3441","h_bukhari_4874"],"ونهران باطنان":["h_muslim_237","h_ahmad_1779","h_bukhari_4874"],"ونهي":["h_muslim_737","h_muslim_739","h_muslim_1130","h_muslim_1588","h_nasai_1084","h_nasai_1101","h_ahmad_3998","h_bukhari_2285"],"ونهي أن":["h_muslim_737","h_muslim_739","h_nasai_1084","h_nasai_1101"],"ونهينا":["h_muslim_817","h_tirmidzi_370","h_abu-dawud_799","h_ahmad_4116","h_bukhari_5879"],"ونهينا عن":["h_muslim_817","h_tirmidzi_370","h_abu-dawud_799","h_ahmad_4116"],"ونهي عن":["h_muslim_1130","h_muslim_1588","h_ahmad_3998","h_bukhari_2285"],"ونهب":["h_muslim_1671"],"ونهب العبيدبين":["h_muslim_1671"],"ونهكت":["h_muslim_1861","h_abu-dawud_3948"],"ونهكت لا":["h_muslim_1861"],"ونهانا":["h_muslim_3352","h_muslim_3566","h_nasai_1868","h_nasai_4038","h_nasai_4039","h_nasai_4052","h_nasai_4224","h_nasai_4824","h_nasai_4953","h_tirmidzi_1715","h_tirmidzi_2666","h_abu-dawud_949","h_ahmad_134","h_ahmad_2299","h_ahmad_3270","h_bukhari_1163","h_bukhari_2265","h_bukhari_4208","h_bukhari_4472","h_bukhari_4899","h_bukhari_4913","h_bukhari_5096","h_bukhari_5449","h_bukhari_5461","h_bukhari_6341","h_darimi_1244","h_ibnu-majah_3387","h_ibnu-majah_3726"],"ونهانا النبي":["h_muslim_3352","h_nasai_4052"],"ونهى أن":["h_muslim_3426","h_nasai_716","h_nasai_5196","h_nasai_5202","h_tirmidzi_1671","h_abu-dawud_3137","h_ibnu-majah_277","h_ibnu-majah_3351"],"ونهانا عن":["h_muslim_3566","h_nasai_1868","h_nasai_4038","h_nasai_4039","h_nasai_4824","h_nasai_4953","h_tirmidzi_1715","h_tirmidzi_2666","h_abu-dawud_949","h_ahmad_134","h_ahmad_2299","h_ahmad_3270","h_bukhari_1163","h_bukhari_2265","h_bukhari_4208","h_bukhari_4472","h_bukhari_4899","h_bukhari_4913","h_bukhari_5096","h_bukhari_5449","h_bukhari_5461","h_bukhari_6341","h_darimi_1244"],"ونهاني":["h_muslim_3617","h_nasai_4854","h_nasai_4856","h_nasai_5020","h_abu-dawud_402","h_abu-dawud_3575","h_ahmad_3091","h_bukhari_3046","h_ibnu-majah_675"],"ونهاني عن":["h_muslim_3617","h_nasai_5020","h_abu-dawud_3575","h_bukhari_3046"],"ونهاره":["h_muslim_3849"],"ونهاره فإذا":["h_muslim_3849"],"ونهرا":["h_muslim_4833","h_abu-dawud_3644"],"ونهرا من":["h_muslim_4833","h_abu-dawud_3644"],"ونهر":["h_muslim_4838","h_ahmad_3549","h_ahmad_3550","h_bukhari_6255","h_ibnu-majah_4279"],"ونهر من":["h_muslim_4838","h_ahmad_3550"],"ونهران ظاهران":["h_nasai_443","h_ahmad_1779","h_ahmad_1780","h_bukhari_2968","h_bukhari_3441"],"ونهزأ":["h_nasai_627"],"ونهزأ به":["h_nasai_627"],"ونهاكم":["h_nasai_3684","h_darimi_417"],"ونهاكم عن":["h_nasai_3684"],"ونهانا رسول":["h_nasai_4224"],"ونهى يومئذ":["h_nasai_4515","h_nasai_4516","h_abu-dawud_3840"],"ونهاني أن":["h_nasai_4854","h_nasai_4856","h_abu-dawud_402","h_abu-dawud_3575","h_ibnu-majah_675"],"ونهيم":["h_nasai_5044"],"ونهيم ونشرب":["h_nasai_5044"],"ونهتني":["h_nasai_5276"],"ونهتني عن":["h_nasai_5276"],"ونهرۙ":["q_54_54"],"ونهى أبو":["h_tirmidzi_1472"],"ونهيك":["h_tirmidzi_1879"],"ونهيك عن":["h_tirmidzi_1879"],"ونهوا":["q_22_41"],"ونهوا عن":["q_22_41"],"ونهى النفس":["q_79_40"],"ونهاهم أن":["h_abu-dawud_517","h_darimi_930"],"ونهيه":["h_abu-dawud_1078","h_abu-dawud_4393"],"ونهيه عن":["h_abu-dawud_1078","h_abu-dawud_4393"],"ونهاهم ثم":["h_abu-dawud_2504"],"ونهيت":["h_abu-dawud_2579","h_ahmad_822"],"ونهيت عن":["h_abu-dawud_2579"],"ونهكت الأموال":["h_abu-dawud_3948"],"ونهى النبي":["h_abu-dawud_4036","h_bukhari_1857","h_bukhari_2005","h_bukhari_2019","h_bukhari_4004"],"ونهيق":["h_abu-dawud_4270"],"ونهيق الحمر":["h_abu-dawud_4270"],"ونهى عنهاو":["h_ahmad_640"],"ونهى ابن":["h_ahmad_653"],"ونهيت فقال":["h_ahmad_822"],"ونهض":["h_ahmad_1535"],"ونهض الناس":["h_ahmad_1535"],"ونهضت":["h_ahmad_1535","h_ahmad_1616"],"ونهضت معهم":["h_ahmad_1535"],"ونهضت فلم":["h_ahmad_1616"],"ونهاه ووعظه":["h_ahmad_2744"],"ونهاني ثم":["h_ahmad_3091"],"ونهر وماء":["h_ahmad_3549"],"ونهينا أن":["h_bukhari_5879"],"ونهر ماء":["h_bukhari_6255"],"ونهاكم عنه":["h_darimi_417"],"ونهاه عنها":["h_darimi_1800"],"ونهاراۙ":["q_71_5"],"ونهارها":["h_ibnu-majah_5"],"ونهارها سواءقال":["h_ibnu-majah_5"],"ونهارها سواء":["h_ibnu-majah_5"],"ونهانا أن":["h_ibnu-majah_3387"],"ونهانا فأمرنا":["h_ibnu-majah_3726"],"ونهر مطرد":["h_ibnu-majah_4279"],"ونوقظك":["h_malik_473"],"ونوقظك فخرج":["h_malik_473"],"ونواء":["h_malik_846","h_muslim_1561","h_nasai_3407","h_bukhari_2198","h_bukhari_2648","h_bukhari_3237","h_bukhari_4275"],"ونواء لأهل":["h_malik_846","h_nasai_3407","h_bukhari_2198","h_bukhari_2648","h_bukhari_3237"],"ونوحا":["q_3_33","q_21_76","q_6_84"],"ونوحا وال":["q_3_33"],"ونور":["h_muslim_1446","h_tirmidzi_3279","h_abu-dawud_2635","h_abu-dawud_3738"],"ونور له":["h_muslim_1446","h_abu-dawud_2635"],"ونواء على":["h_muslim_1561"],"ونوفل":["h_muslim_1698","h_tirmidzi_160"],"ونوفل بن":["h_muslim_1698","h_tirmidzi_160"],"ونوائبه":["h_muslim_3072","h_abu-dawud_2512","h_bukhari_2862"],"ونوائبه وأمرهما":["h_muslim_3072","h_abu-dawud_2512","h_bukhari_2862"],"ونون":["h_muslim_4642","h_abu-dawud_1159","h_bukhari_5734"],"ونون قالوا":["h_muslim_4642","h_bukhari_5734"],"ونون يأكل":["h_muslim_4642","h_bukhari_5734"],"ونودوا":["h_muslim_4711","q_7_43","h_darimi_2348"],"ونودوا أن":["h_muslim_4711","h_darimi_2348"],"ونوم":["h_nasai_127","h_nasai_158","h_nasai_159","h_tirmidzi_89","h_tirmidzi_3251","h_tirmidzi_3252","h_ahmad_1979","h_bukhari_1107","h_ibnu-majah_439"],"ونوم إلا":["h_nasai_127"],"ونوح":["h_nasai_1885"],"ونوح بن":["h_nasai_1885"],"ونوحا اذ":["q_21_76"],"ونوم قال":["h_tirmidzi_89","h_tirmidzi_3252"],"ونواحيها":["h_tirmidzi_1076"],"ونواحيها وإن":["h_tirmidzi_1076"],"ونورا":["h_tirmidzi_3170","h_tirmidzi_3539"],"ونورا في":["h_tirmidzi_3170"],"ونورا من":["h_tirmidzi_3170"],"ونورا عن":["h_tirmidzi_3170"],"ونوم فقلت":["h_tirmidzi_3251"],"ونور وجهك":["h_tirmidzi_3279"],"ونورا لهم":["h_tirmidzi_3539"],"ونورهمۗ":["q_57_19"],"ونورهمۗ والذين":["q_57_19"],"ونون في":["h_abu-dawud_1159"],"ونواصيها":["h_abu-dawud_2115","h_ahmad_1666"],"ونواصيها معقود":["h_abu-dawud_2115","h_ahmad_1666"],"ونور يحكم":["h_abu-dawud_3738"],"ونوائب":["h_ahmad_1079"],"ونوائب الناس":["h_ahmad_1079"],"ونواصيها وقال":["h_ahmad_1666"],"ونوم وجاء":["h_ahmad_1979"],"ونوازع":["h_ahmad_3354"],"ونوازع القبائل":["h_ahmad_3354"],"ونودي":["h_ahmad_3941","h_bukhari_331"],"ونودي في":["h_ahmad_3941","h_bukhari_331"],"ونودوا ان":["q_7_43"],"ونودي بالصلاة":["h_bukhari_331"],"ونوم على":["h_bukhari_1107"],"ونومه":["h_bukhari_1677"],"ونومه فإذا":["h_bukhari_1677"],"ونومي":["h_bukhari_3360"],"ونومي صبيانك":["h_bukhari_3360"],"ونومت":["h_bukhari_3360"],"ونومت صبيانها":["h_bukhari_3360"],"ونواء فهي":["h_bukhari_4275"],"ونوحا هدينا":["q_6_84"],"ونورۚ":["q_5_44"],"ونورۚ يحكم":["q_5_44"],"ونورۙ":["q_5_46"],"ونورۙ ومصدقا":["q_5_46"],"ونية":["h_muslim_2257","h_muslim_3227","h_muslim_3228","h_nasai_3887","h_nasai_3888","h_tirmidzi_532","h_tirmidzi_1516","h_abu-dawud_2056","h_ahmad_264","h_ahmad_4299","h_bukhari_1703","h_bukhari_2575","h_bukhari_2613","h_bukhari_2848","h_bukhari_2951","h_bukhari_3454","h_bukhari_3695","h_darimi_2045"],"ونية وإذا":["h_muslim_2257","h_muslim_3227","h_muslim_3228","h_tirmidzi_1516","h_abu-dawud_2056","h_ahmad_4299","h_bukhari_1703","h_bukhari_2575","h_bukhari_2613","h_bukhari_2848","h_bukhari_2951"],"ونية فإذا":["h_nasai_3887","h_nasai_3888","h_ahmad_264"],"ونيئا":["h_nasai_4047"],"ونيسرك":["q_87_8"],"ونيسرك لليسرىۖ":["q_87_8"],"ونية المأموم":["h_tirmidzi_532"],"ونيط":["h_abu-dawud_3885"],"ونيط عمر":["h_abu-dawud_3885"],"ونيط عثمان":["h_abu-dawud_3885"]}